Workbook

Sheet Summary
A1: Sponsor pipeline v2: follow the money
A2: Built 24 Oct 2026. Tier A = proven spend on our audience; B = serves our audience; C = large/generic (parked).
B4: Companies | C4: Expected value (€) | D4: Won (€)
A5: Tier A | B5: =COUNTIF('Pipeline A-B'!$E$2:$E$132,"A") | C5: =SUMIF('Pipeline A-B'!$E$2:$E$132,"A",'Pipeline A-B'!$P$2:$P$132) | D5: =SUMIFS('Pipeline A-B'!$N$2:$N$132,'Pipeline A-B'!$E$2:$E$132,"A",'Pipeline A-B'!$R$2:$R$132,"Won")
A6: Tier B | B6: =COUNTIF('Pipeline A-B'!$E$2:$E$132,"B") | C6: =SUMIF('Pipeline A-B'!$E$2:$E$132,"B",'Pipeline A-B'!$P$2:$P$132) | D6: =SUMIFS('Pipeline A-B'!$N$2:$N$132,'Pipeline A-B'!$E$2:$E$132,"B",'Pipeline A-B'!$R$2:$R$132,"Won")
A7: Tier C (parked) | B7: =COUNTA('Later (tier C)'!$A$2:$A$70) | C7: =SUM('Later (tier C)'!$P$2:$P$70) | D7: =SUMIF('Later (tier C)'!$R$2:$R$70,"Won",'Later (tier C)'!$N$2:$N$70)
A8: Total | B8: =SUM(B5:B7) | C8: =SUM(C5:C7) | D8: =SUM(D5:D7)
A9: Share of tier A + B | B9: =(B5+B6)/B8
A11: Edition | B11: A + B companies | C11: Expected value (€)
A12: LU | B12: =SUMPRODUCT(--ISNUMBER(SEARCH("LU",'Pipeline A-B'!$D$2:$D$132))) | C12: =SUMPRODUCT(ISNUMBER(SEARCH("LU",'Pipeline A-B'!$D$2:$D$132))*'Pipeline A-B'!$P$2:$P$132)
A13: FR | B13: =SUMPRODUCT(--ISNUMBER(SEARCH("FR",'Pipeline A-B'!$D$2:$D$132))) | C13: =SUMPRODUCT(ISNUMBER(SEARCH("FR",'Pipeline A-B'!$D$2:$D$132))*'Pipeline A-B'!$P$2:$P$132)
A14: CH | B14: =SUMPRODUCT(--ISNUMBER(SEARCH("CH",'Pipeline A-B'!$D$2:$D$132))) | C14: =SUMPRODUCT(ISNUMBER(SEARCH("CH",'Pipeline A-B'!$D$2:$D$132))*'Pipeline A-B'!$P$2:$P$132)
A15: BR | B15: =SUMPRODUCT(--ISNUMBER(SEARCH("BR",'Pipeline A-B'!$D$2:$D$132))) | C15: =SUMPRODUCT(ISNUMBER(SEARCH("BR",'Pipeline A-B'!$D$2:$D$132))*'Pipeline A-B'!$P$2:$P$132)
A16: US | B16: =SUMPRODUCT(--ISNUMBER(SEARCH("US",'Pipeline A-B'!$D$2:$D$132))) | C16: =SUMPRODUCT(ISNUMBER(SEARCH("US",'Pipeline A-B'!$D$2:$D$132))*'Pipeline A-B'!$P$2:$P$132)
A17: IL | B17: =SUMPRODUCT(--ISNUMBER(SEARCH("IL",'Pipeline A-B'!$D$2:$D$132))) | C17: =SUMPRODUCT(ISNUMBER(SEARCH("IL",'Pipeline A-B'!$D$2:$D$132))*'Pipeline A-B'!$P$2:$P$132)
A18: A company with several editions counts in each, so edition rows add up to more than the total.
A20: Status | B20: A + B companies
A21: To contact | B21: =COUNTIF('Pipeline A-B'!$R$2:$R$132,"To contact")
A22: Contacted | B22: =COUNTIF('Pipeline A-B'!$R$2:$R$132,"Contacted")
A23: Replied | B23: =COUNTIF('Pipeline A-B'!$R$2:$R$132,"Replied")
A24: Call booked | B24: =COUNTIF('Pipeline A-B'!$R$2:$R$132,"Call booked")
A25: Proposal sent | B25: =COUNTIF('Pipeline A-B'!$R$2:$R$132,"Proposal sent")
A26: Won | B26: =COUNTIF('Pipeline A-B'!$R$2:$R$132,"Won")
A27: Lost | B27: =COUNTIF('Pipeline A-B'!$R$2:$R$132,"Lost")

Sheet Pipeline A-B
A1: ID | B1: Company | C1: Sector | D1: Editions | E1: Tier | F1: Size | G1: Evidence URL | H1: Evidence | I1: Evidence year | J1: Evidence check | K1: Who to reach | L1: Channel | M1: Offer | N1: Deal value year 1 (€) | O1: Close probability | P1: Expected value (€) | Q1: Priority score | R1: Status | S1: Next action | T1: Next action date | U1: Owner | V1: Capital origin
A2: S179 | B2: Cross Border Wealth | C2: Cross-border wealth adviser (private) | D2: US | E2: A | F2: S | G2: https://expressoemprego.pt/emprego/international-investment-advisor-financial-advisor/2428178 | H2: Wealth Partner tier (D33): Preparing a Lisbon office for US-connected individuals abroad (job ad, May 2026) (prompt 15) | I2: 2026 | J2: Search result | K2: Head of international or Portugal desk | L2: LinkedIn (named role), then company email | M2: Wealth Partner | N2: =INDEX(Settings!$B$4:$B$15,MATCH(M2,Settings!$A$4:$A$15,0)) | O2: =IF(E2="A",IF(I2>=2022,Settings!$B$18,Settings!$B$19),IF(E2="B",Settings!$B$20,Settings!$B$21))+IF(F2="S",Settings!$B$22,0) | P2: =N2*O2 | Q2: =P2*INDEX(Settings!$B$25:$B$27,MATCH(F2,Settings!$A$25:$A$27,0)) | R2: To contact | S2: Touch 1 (sponsors/outreach/v3) | T2: 2026-11-09 | U2: Partner | V2: United States
A3: S180 | B3: Euro American Financial Advisors | C3: Cross-border wealth adviser (private) | D3: US | E3: A | F3: S | G3: https://www.expatfocus.com/?p=51322 | H3: Wealth Partner tier (D33): Panel on moving to Portugal at the 2026 US Expats Financial Conference (prompt 15) | I3: 2026 | J3: Search result | K3: Head of international or Portugal desk | L3: LinkedIn (named role), then company email | M3: Wealth Partner | N3: =INDEX(Settings!$B$4:$B$15,MATCH(M3,Settings!$A$4:$A$15,0)) | O3: =IF(E3="A",IF(I3>=2022,Settings!$B$18,Settings!$B$19),IF(E3="B",Settings!$B$20,Settings!$B$21))+IF(F3="S",Settings!$B$22,0) | P3: =N3*O3 | Q3: =P3*INDEX(Settings!$B$25:$B$27,MATCH(F3,Settings!$A$25:$A$27,0)) | R3: To contact | S3: Touch 1 (sponsors/outreach/v3) | T3: 2026-11-09 | U3: Partner | V3: United States
A4: S181 | B4: Finalib | C4: Wealth adviser (private) | D4: FR | E4: A | F4: S | G4: https://finalib.fr/blog/fiscalite/expatriation-fiscale-2026-quitter-france-impots | H4: Wealth Partner tier (D33): Content on tax expatriation from France to Portugal (2026) (prompt 15) | I4: 2026 | J4: Search result | K4: Head of international or Portugal desk | L4: LinkedIn (named role), then company email | M4: Wealth Partner | N4: =INDEX(Settings!$B$4:$B$15,MATCH(M4,Settings!$A$4:$A$15,0)) | O4: =IF(E4="A",IF(I4>=2022,Settings!$B$18,Settings!$B$19),IF(E4="B",Settings!$B$20,Settings!$B$21))+IF(F4="S",Settings!$B$22,0) | P4: =N4*O4 | Q4: =P4*INDEX(Settings!$B$25:$B$27,MATCH(F4,Settings!$A$25:$A$27,0)) | R4: To contact | S4: Touch 1 (sponsors/outreach/v3) | T4: 2026-11-09 | U4: Partner | V4: France
A5: S182 | B5: Green Ocean Global Advisors | C5: Cross-border wealth adviser (private) | D5: US | E5: A | F5: S | G5: https://podcastaddict.com/episode/https%3A%2F%2Fwww.podtrac.com%2Fpts%2Fredirect.mp3%2Ftraffic.megaphone.fm%2FTPGL5408537107.mp3&podcastId=6068358 | H5: Wealth Partner tier (D33): Lisbon-based cross-border planning for Americans in Portugal (podcast, June 2026) (prompt 15) | I5: 2026 | J5: Search result | K5: Head of international or Portugal desk | L5: LinkedIn (named role), then company email | M5: Wealth Partner | N5: =INDEX(Settings!$B$4:$B$15,MATCH(M5,Settings!$A$4:$A$15,0)) | O5: =IF(E5="A",IF(I5>=2022,Settings!$B$18,Settings!$B$19),IF(E5="B",Settings!$B$20,Settings!$B$21))+IF(F5="S",Settings!$B$22,0) | P5: =N5*O5 | Q5: =P5*INDEX(Settings!$B$25:$B$27,MATCH(F5,Settings!$A$25:$A$27,0)) | R5: To contact | S5: Touch 1 (sponsors/outreach/v3) | T5: 2026-11-09 | U5: Partner | V5: United States
A6: S183 | B6: Liberty Atlantic Advisors | C6: Cross-border wealth adviser (private) | D6: US | E6: A | F6: S | G6: https://www.kiplinger.com/author/ricardo-jesus-mba | H6: Wealth Partner tier (D33): Fiduciary residency and international tax planning for Americans in Portugal (prompt 15) | I6: 2026 | J6: Search result | K6: Head of international or Portugal desk | L6: LinkedIn (named role), then company email | M6: Wealth Partner | N6: =INDEX(Settings!$B$4:$B$15,MATCH(M6,Settings!$A$4:$A$15,0)) | O6: =IF(E6="A",IF(I6>=2022,Settings!$B$18,Settings!$B$19),IF(E6="B",Settings!$B$20,Settings!$B$21))+IF(F6="S",Settings!$B$22,0) | P6: =N6*O6 | Q6: =P6*INDEX(Settings!$B$25:$B$27,MATCH(F6,Settings!$A$25:$A$27,0)) | R6: To contact | S6: Touch 1 (sponsors/outreach/v3) | T6: 2026-11-09 | U6: Partner | V6: United States
A7: S184 | B7: Lisbon Family Office | C7: Family office (private) | D7: LU, FR, CH, BR, US, IL | E7: A | F7: S | G7: https://altss.com/profile/lisbon-family-office | H7: Wealth Partner tier (D33): CMVM-regulated multi-family office; existing MFOs mainly target non-resident clients (prompt 15) | I7: 2025 | J7: Search result | K7: Head of international or Portugal desk | L7: LinkedIn (named role), then company email | M7: Wealth Partner | N7: =INDEX(Settings!$B$4:$B$15,MATCH(M7,Settings!$A$4:$A$15,0)) | O7: =IF(E7="A",IF(I7>=2022,Settings!$B$18,Settings!$B$19),IF(E7="B",Settings!$B$20,Settings!$B$21))+IF(F7="S",Settings!$B$22,0) | P7: =N7*O7 | Q7: =P7*INDEX(Settings!$B$25:$B$27,MATCH(F7,Settings!$A$25:$A$27,0)) | R7: To contact | S7: Touch 1 (sponsors/outreach/v3) | T7: 2026-11-09 | U7: Partner | V7: Portugal
A8: S185 | B8: Neofa | C8: International tax adviser (private) | D8: FR | E8: A | F8: S | G8: https://neofa.com/fr/fiscalite/fiscalite-des-particuliers/conseil-fiscalite-internationale/exit-tax-france/ | H8: Wealth Partner tier (D33): French international tax firm; guides on leaving France for Spain and Portugal (prompt 15) | I8: 2026 | J8: Search result | K8: Partner, private clients | L8: LinkedIn (named role), then company email | M8: Wealth Partner | N8: =INDEX(Settings!$B$4:$B$15,MATCH(M8,Settings!$A$4:$A$15,0)) | O8: =IF(E8="A",IF(I8>=2022,Settings!$B$18,Settings!$B$19),IF(E8="B",Settings!$B$20,Settings!$B$21))+IF(F8="S",Settings!$B$22,0) | P8: =N8*O8 | Q8: =P8*INDEX(Settings!$B$25:$B$27,MATCH(F8,Settings!$A$25:$A$27,0)) | R8: To contact | S8: Touch 1 (sponsors/outreach/v3) | T8: 2026-11-09 | U8: Partner | V8: France
A9: S170 | B9: Millennium bcp Private Banking | C9: Private banking / wealth / private client | D9: LU, FR, CH, BR, US, IL | E9: A | F9: L | G9: https://chambers.com/department/millennium-bcp-private-banks-high-net-worth-21:2699:174:1:249515 | H9: Ranked by Chambers in private banking (High Net Worth). | I9: 2026 | J9: Search result, not opened | K9: Head of private clients / Portugal desk | L9: Website: millenniumbcp.pt | M9: Wealth Partner | N9: =INDEX(Settings!$B$4:$B$15,MATCH(M9,Settings!$A$4:$A$15,0)) | O9: =IF(E9="A",IF(I9>=2022,Settings!$B$18,Settings!$B$19),IF(E9="B",Settings!$B$20,Settings!$B$21))+IF(F9="S",Settings!$B$22,0) | P9: =N9*O9 | Q9: =P9*INDEX(Settings!$B$25:$B$27,MATCH(F9,Settings!$A$25:$A$27,0)) | R9: Not contacted | S9: Approach with brochure (D40) | U9: Partner | V9: not assessed
A10: S186 | B10: Banco ATLANTICO Europa | C10: Bank (private) | D10: LU, FR, CH, BR, US, IL | E10: A | F10: M | G10: https://www.portugalresident.com/the-bank-for-people-of-the-world-in-portugal/ | H10: Wealth Partner tier (D33): Paid sponsored text in Portugal Resident aimed at non-residents: proven spend on an international audience (prompt 15) | I10: 2025 | J10: Search result | K10: Head of international or Portugal desk | L10: LinkedIn (named role), then company email | M10: Wealth Partner | N10: =INDEX(Settings!$B$4:$B$15,MATCH(M10,Settings!$A$4:$A$15,0)) | O10: =IF(E10="A",IF(I10>=2022,Settings!$B$18,Settings!$B$19),IF(E10="B",Settings!$B$20,Settings!$B$21))+IF(F10="S",Settings!$B$22,0) | P10: =N10*O10 | Q10: =P10*INDEX(Settings!$B$25:$B$27,MATCH(F10,Settings!$A$25:$A$27,0)) | R10: To contact | S10: Touch 1 (sponsors/outreach/v3) | T10: 2026-11-09 | U10: Partner | V10: Angola
A11: S187 | B11: Blacktower Financial Management | C11: Cross-border wealth adviser (private) | D11: US | E11: A | F11: M | G11: https://international-adviser.com/blacktower-unveils-portugal-expat-service-for-us-nationals/ | H11: Wealth Partner tier (D33): American desk for US nationals relocating to Portugal (prompt 15) | I11: 2022 | J11: Search result | K11: Head of international or Portugal desk | L11: LinkedIn (named role), then company email | M11: Wealth Partner | N11: =INDEX(Settings!$B$4:$B$15,MATCH(M11,Settings!$A$4:$A$15,0)) | O11: =IF(E11="A",IF(I11>=2022,Settings!$B$18,Settings!$B$19),IF(E11="B",Settings!$B$20,Settings!$B$21))+IF(F11="S",Settings!$B$22,0) | P11: =N11*O11 | Q11: =P11*INDEX(Settings!$B$25:$B$27,MATCH(F11,Settings!$A$25:$A$27,0)) | R11: To contact | S11: Touch 1 (sponsors/outreach/v3) | T11: 2026-11-09 | U11: Partner | V11: Gibraltar / UK
A12: S188 | B12: Dixcart (Portugal) | C12: Corporate and family-office services (private) | D12: LU, FR, CH, US, IL | E12: A | F12: M | G12: https://www.dixcart.com/es/?p=612 | H12: Wealth Partner tier (D33): Family office and relocation services in Portugal for international families (prompt 15) | I12: 2025 | J12: Search result | K12: Head of international or Portugal desk | L12: LinkedIn (named role), then company email | M12: Wealth Partner | N12: =INDEX(Settings!$B$4:$B$15,MATCH(M12,Settings!$A$4:$A$15,0)) | O12: =IF(E12="A",IF(I12>=2022,Settings!$B$18,Settings!$B$19),IF(E12="B",Settings!$B$20,Settings!$B$21))+IF(F12="S",Settings!$B$22,0) | P12: =N12*O12 | Q12: =P12*INDEX(Settings!$B$25:$B$27,MATCH(F12,Settings!$A$25:$A$27,0)) | R12: To contact | S12: Touch 1 (sponsors/outreach/v3) | T12: 2026-11-09 | U12: Partner | V12: United Kingdom
A13: S189 | B13: Ombria Algarve (Viceroy Residences) | C13: Prime developer (private) | D13: FR, LU, CH, US | E13: A | F13: M | G13: https://www.portugalresident.com/80-of-viceroy-residents-already-sold-at-ombria/ | H13: Wealth Partner tier (D33): Algarve resort; buyers British, Dutch, Portuguese, French and American (prompt 15) | I13: 2024 | J13: Search result | K13: Sales or marketing director | L13: LinkedIn (named role), then company email | M13: Wealth Partner | N13: =INDEX(Settings!$B$4:$B$15,MATCH(M13,Settings!$A$4:$A$15,0)) | O13: =IF(E13="A",IF(I13>=2022,Settings!$B$18,Settings!$B$19),IF(E13="B",Settings!$B$20,Settings!$B$21))+IF(F13="S",Settings!$B$22,0) | P13: =N13*O13 | Q13: =P13*INDEX(Settings!$B$25:$B$27,MATCH(F13,Settings!$A$25:$A$27,0)) | R13: To contact | S13: Touch 1 (sponsors/outreach/v3) | T13: 2026-11-09 | U13: Partner | V13: Finland
A14: S190 | B14: Overseas (Karl Lagerfeld Residences Lisbon) | C14: Prime developer (private) | D14: FR, BR, US, LU, CH | E14: A | F14: M | G14: https://econews.pt/2026/06/04/karl-lagerfeld-residences-launches-sales-in-10-markets/ | H14: Wealth Partner tier (D33): Branded residences in Lisbon marketed in 10 markets incl. France, the US and Brazil (June 2026) (prompt 15) | I14: 2026 | J14: Search result | K14: Sales or marketing director | L14: LinkedIn (named role), then company email | M14: Wealth Partner | N14: =INDEX(Settings!$B$4:$B$15,MATCH(M14,Settings!$A$4:$A$15,0)) | O14: =IF(E14="A",IF(I14>=2022,Settings!$B$18,Settings!$B$19),IF(E14="B",Settings!$B$20,Settings!$B$21))+IF(F14="S",Settings!$B$22,0) | P14: =N14*O14 | Q14: =P14*INDEX(Settings!$B$25:$B$27,MATCH(F14,Settings!$A$25:$A$27,0)) | R14: To contact | S14: Touch 1 (sponsors/outreach/v3) | T14: 2026-11-09 | U14: Partner | V14: Portugal
A15: S191 | B15: Rivage Properties (The View II) | C15: Prime developer (private) | D15: LU, FR, CH | E15: A | F15: M | G15: https://www.essential-business.pt/2024/06/14/rivage-invests-e20-million-in-homes-near-porto/ | H15: Wealth Partner tier (D33): Apartments by the Douro from 755,000 € to 1.5 M€ near Porto (prompt 15) | I15: 2024 | J15: Search result | K15: Sales or marketing director | L15: LinkedIn (named role), then company email | M15: Wealth Partner | N15: =INDEX(Settings!$B$4:$B$15,MATCH(M15,Settings!$A$4:$A$15,0)) | O15: =IF(E15="A",IF(I15>=2022,Settings!$B$18,Settings!$B$19),IF(E15="B",Settings!$B$20,Settings!$B$21))+IF(F15="S",Settings!$B$22,0) | P15: =N15*O15 | Q15: =P15*INDEX(Settings!$B$25:$B$27,MATCH(F15,Settings!$A$25:$A$27,0)) | R15: To contact | S15: Touch 1 (sponsors/outreach/v3) | T15: 2026-11-09 | U15: Partner | V15: Portugal
A16: S192 | B16: Sable International | C16: Cross-border wealth adviser (private) | D16: US | E16: A | F16: M | G16: https://www.sableinternational.com/blog/living-in-portugal--is-your-wealth-plan-keeping-up | H16: Wealth Partner tier (D33): Consultation campaign for people in Portugal with US, UK or South African ties (Nov 2026) (prompt 15) | I16: 2026 | J16: Search result | K16: Head of international or Portugal desk | L16: LinkedIn (named role), then company email | M16: Wealth Partner | N16: =INDEX(Settings!$B$4:$B$15,MATCH(M16,Settings!$A$4:$A$15,0)) | O16: =IF(E16="A",IF(I16>=2022,Settings!$B$18,Settings!$B$19),IF(E16="B",Settings!$B$20,Settings!$B$21))+IF(F16="S",Settings!$B$22,0) | P16: =N16*O16 | Q16: =P16*INDEX(Settings!$B$25:$B$27,MATCH(F16,Settings!$A$25:$A$27,0)) | R16: To contact | S16: Touch 1 (sponsors/outreach/v3) | T16: 2026-11-09 | U16: Partner | V16: United Kingdom
A17: S193 | B17: Sovereign Group (Portugal) | C17: Corporate and tax services (private) | D17: LU, FR, CH, US, IL | E17: A | F17: M | G17: https://www.sovereigngroup.com/news/the-ifici-a-sharper-edge-for-attracting-global-talent-to-portugal/ | H17: Wealth Partner tier (D33): Publishes IFICI guidance for people relocating to Portugal (prompt 15) | I17: 2025 | J17: Search result | K17: Partner, private clients | L17: LinkedIn (named role), then company email | M17: Wealth Partner | N17: =INDEX(Settings!$B$4:$B$15,MATCH(M17,Settings!$A$4:$A$15,0)) | O17: =IF(E17="A",IF(I17>=2022,Settings!$B$18,Settings!$B$19),IF(E17="B",Settings!$B$20,Settings!$B$21))+IF(F17="S",Settings!$B$22,0) | P17: =N17*O17 | Q17: =P17*INDEX(Settings!$B$25:$B$27,MATCH(F17,Settings!$A$25:$A$27,0)) | R17: To contact | S17: Touch 1 (sponsors/outreach/v3) | T17: 2026-11-09 | U17: Partner | V17: Gibraltar
A18: S157 | B18: Ando Living | C18: Developer (Comporta) | D18: LU, FR, CH, BR, US, IL | E18: A | F18: L | G18: https://www.idealista.pt/en/news/node/71011 | H18: First Comporta project: 16 luxury villas for international buyers. | I18: 2026 | J18: Search result, not opened | K18: Fundadores / vendas | L18: Website contact / LinkedIn | M18: Area placement (Prime) | N18: =INDEX(Settings!$B$4:$B$15,MATCH(M18,Settings!$A$4:$A$15,0)) | O18: =IF(E18="A",IF(I18>=2022,Settings!$B$18,Settings!$B$19),IF(E18="B",Settings!$B$20,Settings!$B$21))+IF(F18="S",Settings!$B$22,0) | P18: =N18*O18 | Q18: =P18*INDEX(Settings!$B$25:$B$27,MATCH(F18,Settings!$A$25:$A$27,0)) | R18: Not contacted | S18: Approach with brochure (D40) | U18: Partner | V18: not assessed
A19: S156 | B19: Herdade da Comporta | C19: Developer (Comporta) | D19: LU, FR, CH, BR, US, IL | E19: A | F19: L | G19: https://www.idealista.pt/en/news/node/61843 | H19: The estate bought by the Amorim family and partners; selling land for luxury tourism and residential projects. | I19: 2026 | J19: Search result, not opened | K19: Administração / desenvolvimento | L19: Website: herdadedacomporta.pt | M19: Area placement (Prime) | N19: =INDEX(Settings!$B$4:$B$15,MATCH(M19,Settings!$A$4:$A$15,0)) | O19: =IF(E19="A",IF(I19>=2022,Settings!$B$18,Settings!$B$19),IF(E19="B",Settings!$B$20,Settings!$B$21))+IF(F19="S",Settings!$B$22,0) | P19: =N19*O19 | Q19: =P19*INDEX(Settings!$B$25:$B$27,MATCH(F19,Settings!$A$25:$A$27,0)) | R19: Not contacted | S19: Approach with brochure (D40) | U19: Partner | V19: not assessed
A20: S178 | B20: OneMark Properties | C20: Developer (Lisbon, Grândola, Sines; Porto and Algarve planned) | D20: LU, FR, CH, BR, US, IL | E20: A | F20: L | G20: https://www.idealista.pt/news/node/75369 | H20: Founded early 2026 by José Cardoso Botelho (ex-Vanguard CEO); 7 projects in study (ultraluxury, luxury, premium, flex living, mid); initial 100 M€; targets high-net-worth buyers incl. Gulf investors. Pre-launch: ideal Founding Partner | I20: 2026 | J20: Opened | K20: Founder / CEO | L20: Website: to confirm | M20: Area placement (Prime) + launch | N20: =INDEX(Settings!$B$4:$B$15,MATCH(M20,Settings!$A$4:$A$15,0)) | O20: =IF(E20="A",IF(I20>=2022,Settings!$B$18,Settings!$B$19),IF(E20="B",Settings!$B$20,Settings!$B$21))+IF(F20="S",Settings!$B$22,0) | P20: =N20*O20 | Q20: =P20*INDEX(Settings!$B$25:$B$27,MATCH(F20,Settings!$A$25:$A$27,0)) | R20: Not contacted | S20: Private demo (prompt 26) then approach | U20: Partner | V20: not assessed
A21: S159 | B21: Vale do Lobo | C21: Developer (Algarve · Triângulo Dourado) | D21: LU, FR, CH, BR, US, IL | E21: A | F21: L | G21: https://www.idealista.pt/en/news/luxury-real-estate-in-portugal/2025/02/06/67912-vale-do-lobo-in-the-algarve-invests-over-eu200-million-in-luxury-homes | H21: Investing over 200 M€ in new luxury homes; The Residences at Vale do Lobo 40% reserved at groundbreaking. | I21: 2026 | J21: Search result, not opened | K21: Direção de vendas internacionais | L21: Website: valedolobo.com | M21: Area placement (Prime) | N21: =INDEX(Settings!$B$4:$B$15,MATCH(M21,Settings!$A$4:$A$15,0)) | O21: =IF(E21="A",IF(I21>=2022,Settings!$B$18,Settings!$B$19),IF(E21="B",Settings!$B$20,Settings!$B$21))+IF(F21="S",Settings!$B$22,0) | P21: =N21*O21 | Q21: =P21*INDEX(Settings!$B$25:$B$27,MATCH(F21,Settings!$A$25:$A$27,0)) | R21: Not contacted | S21: Approach with brochure (D40) | U21: Partner | V21: not assessed
A22: S194 | B22: Bradesco Europa (Luxembourg) | C22: Private bank (private) | D22: BR, LU | E22: A | F22: L | G22: https://www.suno.com.br/noticias/bradesco-estuda-atender-milionarios-portugal | H22: Wealth Partner tier (D33): Luxembourg unit serves Brazilian clients who moved to Portugal; studying a Portugal office (prompt 15) | I22: 2026 | J22: Search result | K22: Head of international or Portugal desk | L22: LinkedIn (named role), then company email | M22: Wealth Partner | N22: =INDEX(Settings!$B$4:$B$15,MATCH(M22,Settings!$A$4:$A$15,0)) | O22: =IF(E22="A",IF(I22>=2022,Settings!$B$18,Settings!$B$19),IF(E22="B",Settings!$B$20,Settings!$B$21))+IF(F22="S",Settings!$B$22,0) | P22: =N22*O22 | Q22: =P22*INDEX(Settings!$B$25:$B$27,MATCH(F22,Settings!$A$25:$A$27,0)) | R22: To contact | S22: Touch 1 (sponsors/outreach/v3) | T22: 2026-11-09 | U22: Partner | V22: Brazil
A23: S195 | B23: Degroof Petercam Luxembourg | C23: Private bank (private) | D23: LU, FR | E23: A | F23: L | G23: https://www.degroofpetercam.com/en-lu/resident-in-portugal | H23: Wealth Partner tier (D33): Dedicated 'Resident in Portugal' offer and team from Luxembourg (prompt 15) | I23: 2026 | J23: Search result | K23: Head of international or Portugal desk | L23: LinkedIn (named role), then company email | M23: Wealth Partner | N23: =INDEX(Settings!$B$4:$B$15,MATCH(M23,Settings!$A$4:$A$15,0)) | O23: =IF(E23="A",IF(I23>=2022,Settings!$B$18,Settings!$B$19),IF(E23="B",Settings!$B$20,Settings!$B$21))+IF(F23="S",Settings!$B$22,0) | P23: =N23*O23 | Q23: =P23*INDEX(Settings!$B$25:$B$27,MATCH(F23,Settings!$A$25:$A$27,0)) | R23: To contact | S23: Touch 1 (sponsors/outreach/v3) | T23: 2026-11-09 | U23: Partner | V23: Belgium
A24: S196 | B24: Discovery Land Company (Costa Terra Golf & Ocean Club) | C24: Prime developer (private) | D24: US, FR, CH, LU | E24: A | F24: L | G24: https://www.idealista.com/news/etiquetas/comporta | H24: Wealth Partner tier (D33): Costa Terra project in Melides (Grândola) selling plots to international buyers (prompt 15) | I24: 2024 | J24: Search result | K24: Sales or marketing director | L24: LinkedIn (named role), then company email | M24: Wealth Partner | N24: =INDEX(Settings!$B$4:$B$15,MATCH(M24,Settings!$A$4:$A$15,0)) | O24: =IF(E24="A",IF(I24>=2022,Settings!$B$18,Settings!$B$19),IF(E24="B",Settings!$B$20,Settings!$B$21))+IF(F24="S",Settings!$B$22,0) | P24: =N24*O24 | Q24: =P24*INDEX(Settings!$B$25:$B$27,MATCH(F24,Settings!$A$25:$A$27,0)) | R24: To contact | S24: Touch 1 (sponsors/outreach/v3) | T24: 2026-11-09 | U24: Partner | V24: United States
A25: S197 | B25: Edmond de Rothschild | C25: Private bank (private) | D25: CH, LU, FR | E25: A | F25: L | G25: https://www.bloomberglinea.com.br/2025/03/26/de-saida-do-brasil-julius-baer-planeja-abrir-escritorio-em-lisboa-e-mira-estrangeiros/ | H25: Wealth Partner tier (D33): Listed among private banks present in Lisbon serving foreigners (prompt 15) | I25: 2025 | J25: Search result | K25: Head of international or Portugal desk | L25: LinkedIn (named role), then company email | M25: Wealth Partner | N25: =INDEX(Settings!$B$4:$B$15,MATCH(M25,Settings!$A$4:$A$15,0)) | O25: =IF(E25="A",IF(I25>=2022,Settings!$B$18,Settings!$B$19),IF(E25="B",Settings!$B$20,Settings!$B$21))+IF(F25="S",Settings!$B$22,0) | P25: =N25*O25 | Q25: =P25*INDEX(Settings!$B$25:$B$27,MATCH(F25,Settings!$A$25:$A$27,0)) | R25: To contact | S25: Touch 1 (sponsors/outreach/v3) | T25: 2026-11-09 | U25: Partner | V25: Switzerland
A26: S198 | B26: Indosuez Wealth Management | C26: Private bank (private) | D26: LU, FR, CH | E26: A | F26: L | G26: https://www.privatebankerinternational.com/newsletters/indosuez-wealth-management-sets-up-branch-in-portugal | H26: Wealth Partner tier (D33): Lisbon branch opened 2024 for family offices, entrepreneurs and expatriates; Portuguese desk in Luxembourg (prompt 15) | I26: 2024 | J26: Search result | K26: Head of international or Portugal desk | L26: LinkedIn (named role), then company email | M26: Wealth Partner | N26: =INDEX(Settings!$B$4:$B$15,MATCH(M26,Settings!$A$4:$A$15,0)) | O26: =IF(E26="A",IF(I26>=2022,Settings!$B$18,Settings!$B$19),IF(E26="B",Settings!$B$20,Settings!$B$21))+IF(F26="S",Settings!$B$22,0) | P26: =N26*O26 | Q26: =P26*INDEX(Settings!$B$25:$B$27,MATCH(F26,Settings!$A$25:$A$27,0)) | R26: To contact | S26: Touch 1 (sponsors/outreach/v3) | T26: 2026-11-09 | U26: Partner | V26: France (Crédit Agricole)
A27: S199 | B27: Morais Leitão | C27: Law firm, private clients (private) | D27: LU, FR, CH, BR, US, IL | E27: A | F27: L | G27: https://www.internationaltaxreview.com/itrworldtax/firms/morais-leitao-galvao-teles-soares-da-silva-associados-portugal | H27: Wealth Partner tier (D33): Tax practice with private clients among its clients (prompt 15) | I27: 2026 | J27: Search result | K27: Partner, private clients | L27: LinkedIn (named role), then company email | M27: Wealth Partner | N27: =INDEX(Settings!$B$4:$B$15,MATCH(M27,Settings!$A$4:$A$15,0)) | O27: =IF(E27="A",IF(I27>=2022,Settings!$B$18,Settings!$B$19),IF(E27="B",Settings!$B$20,Settings!$B$21))+IF(F27="S",Settings!$B$22,0) | P27: =N27*O27 | Q27: =P27*INDEX(Settings!$B$25:$B$27,MATCH(F27,Settings!$A$25:$A$27,0)) | R27: To contact | S27: Touch 1 (sponsors/outreach/v3) | T27: 2026-11-09 | U27: Partner | V27: Portugal
A28: S200 | B28: Union Bancaire Privée (UBP) | C28: Private bank (private) | D28: CH, BR | E28: A | F28: L | G28: https://www.bloombergquint.com/onweb/rich-brazilians-moving-to-portugal-pull-local-bankers-with-them | H28: Wealth Partner tier (D33): Lisbon office for wealthy clients moving to Portugal; bought Millennium Banque Privée (Geneva) (prompt 15) | I28: 2024 | J28: Search result | K28: Head of international or Portugal desk | L28: LinkedIn (named role), then company email | M28: Wealth Partner | N28: =INDEX(Settings!$B$4:$B$15,MATCH(M28,Settings!$A$4:$A$15,0)) | O28: =IF(E28="A",IF(I28>=2022,Settings!$B$18,Settings!$B$19),IF(E28="B",Settings!$B$20,Settings!$B$21))+IF(F28="S",Settings!$B$22,0) | P28: =N28*O28 | Q28: =P28*INDEX(Settings!$B$25:$B$27,MATCH(F28,Settings!$A$25:$A$27,0)) | R28: To contact | S28: Touch 1 (sponsors/outreach/v3) | T28: 2026-11-09 | U28: Partner | V28: Switzerland
A29: S201 | B29: VdA Vieira de Almeida | C29: Law firm, private clients (private) | D29: LU, FR, CH, BR, US, IL | E29: A | F29: L | G29: https://chambers.com/department/vda-vieira-de-almeida-private-wealth-law-high-net-worth-21:2633:174:1:3970 | H29: Wealth Partner tier (D33): Ranked private wealth practice advising international family offices, private banks and UHNW individuals (prompt 15) | I29: 2026 | J29: Search result | K29: Partner, private clients | L29: LinkedIn (named role), then company email | M29: Wealth Partner | N29: =INDEX(Settings!$B$4:$B$15,MATCH(M29,Settings!$A$4:$A$15,0)) | O29: =IF(E29="A",IF(I29>=2022,Settings!$B$18,Settings!$B$19),IF(E29="B",Settings!$B$20,Settings!$B$21))+IF(F29="S",Settings!$B$22,0) | P29: =N29*O29 | Q29: =P29*INDEX(Settings!$B$25:$B$27,MATCH(F29,Settings!$A$25:$A$27,0)) | R29: To contact | S29: Touch 1 (sponsors/outreach/v3) | T29: 2026-11-09 | U29: Partner | V29: Portugal
A30: S169 | B30: Andersen Portugal | C30: Estruturação | D30: Todos os países · advogados em Portugal | E30: A | F30: L | G30: https://chambers.com/department/andersen-private-wealth-law-high-net-worth-21:2633:174:1:22620317 | H30: Ranked in private wealth law. | I30: 2026 | J30: Search result, not opened | K30: Private client | L30: Website: pt.andersen.com | M30: Journey checkpoint | N30: =INDEX(Settings!$B$4:$B$15,MATCH(M30,Settings!$A$4:$A$15,0)) | O30: =IF(E30="A",IF(I30>=2022,Settings!$B$18,Settings!$B$19),IF(E30="B",Settings!$B$20,Settings!$B$21))+IF(F30="S",Settings!$B$22,0) | P30: =N30*O30 | Q30: =P30*INDEX(Settings!$B$25:$B$27,MATCH(F30,Settings!$A$25:$A$27,0)) | R30: Not contacted | S30: Approach with brochure (D40) | U30: Partner | V30: not assessed
A31: S166 | B31: BTG Pactual | C31: Estruturação (×1.5) | D31: Brasil | E31: A | F31: L | G31: https://www.essential-business.pt/2019/12/08/btg-pactual-enters-portuguese-banking-market/ | H31: Entered Portuguese banking; expanding European real estate. | I31: 2026 | J31: Search result, not opened | K31: Wealth / Europa | L31: Website: btgpactual.com | M31: Journey checkpoint | N31: =INDEX(Settings!$B$4:$B$15,MATCH(M31,Settings!$A$4:$A$15,0)) | O31: =IF(E31="A",IF(I31>=2022,Settings!$B$18,Settings!$B$19),IF(E31="B",Settings!$B$20,Settings!$B$21))+IF(F31="S",Settings!$B$22,0) | P31: =N31*O31 | Q31: =P31*INDEX(Settings!$B$25:$B$27,MATCH(F31,Settings!$A$25:$A$27,0)) | R31: Not contacted | S31: Approach with brochure (D40) | U31: Partner | V31: not assessed
A32: S168 | B32: CMS Portugal | C32: Estruturação | D32: Todos os países · advogados em Portugal | E32: A | F32: L | G32: https://cms.law/en/prt/news-information/cms-portugal-and-nuno-figueiroa-santos-highlighted-in-the-chambers-and-partners-high-net-worth-guide | H32: Highlighted in Chambers High Net Worth. | I32: 2026 | J32: Search result, not opened | K32: Private client | L32: Website: cms.law | M32: Journey checkpoint | N32: =INDEX(Settings!$B$4:$B$15,MATCH(M32,Settings!$A$4:$A$15,0)) | O32: =IF(E32="A",IF(I32>=2022,Settings!$B$18,Settings!$B$19),IF(E32="B",Settings!$B$20,Settings!$B$21))+IF(F32="S",Settings!$B$22,0) | P32: =N32*O32 | Q32: =P32*INDEX(Settings!$B$25:$B$27,MATCH(F32,Settings!$A$25:$A$27,0)) | R32: Not contacted | S32: Approach with brochure (D40) | U32: Partner | V32: not assessed
A33: S173 | B33: Cleerly | C33: Reforma em Portugal | D33: França | E33: A | F33: L | G33: https://cleerly.fr/retraite/portugal | H33: Wealth-management firm publishing guides on retiring to Portugal. | I33: 2026 | J33: Opened | K33: Marketing | L33: Website: cleerly.fr | M33: Journey checkpoint | N33: =INDEX(Settings!$B$4:$B$15,MATCH(M33,Settings!$A$4:$A$15,0)) | O33: =IF(E33="A",IF(I33>=2022,Settings!$B$18,Settings!$B$19),IF(E33="B",Settings!$B$20,Settings!$B$21))+IF(F33="S",Settings!$B$22,0) | P33: =N33*O33 | Q33: =P33*INDEX(Settings!$B$25:$B$27,MATCH(F33,Settings!$A$25:$A$27,0)) | R33: Not contacted | S33: Approach with brochure (D40) | U33: Partner | V33: not assessed
A34: S171 | B34: Compassurance | C34: 2.º pilar ao sair da Suíça | D34: Suíça | E34: A | F34: L | G34: https://compassurance.ch/retirer-2eme-pilier-quitter-suisse/ | H34: Free expert audit of the 2nd pillar before leaving Switzerland: amount, net tax, canton strategy. | I34: 2026 | J34: Opened | K34: Expert team | L34: Website: compassurance.ch | M34: Journey checkpoint | N34: =INDEX(Settings!$B$4:$B$15,MATCH(M34,Settings!$A$4:$A$15,0)) | O34: =IF(E34="A",IF(I34>=2022,Settings!$B$18,Settings!$B$19),IF(E34="B",Settings!$B$20,Settings!$B$21))+IF(F34="S",Settings!$B$22,0) | P34: =N34*O34 | Q34: =P34*INDEX(Settings!$B$25:$B$27,MATCH(F34,Settings!$A$25:$A$27,0)) | R34: Not contacted | S34: Approach with brochure (D40) | U34: Partner | V34: not assessed
A35: S175 | B35: Creative Planning International | C35: Estruturação (×1.5) | D35: EUA | E35: A | F35: L | G35: https://creativeplanning.com/international/insights/financial-planning/9-critical-financial-planning-considerations-for-american-expats-living-in-portugal/ | H35: US expat wealth services covering Portugal (households with US$500k+ in US assets). | I35: 2026 | J35: Opened | K35: International team | L35: Website: creativeplanning.com | M35: Journey checkpoint | N35: =INDEX(Settings!$B$4:$B$15,MATCH(M35,Settings!$A$4:$A$15,0)) | O35: =IF(E35="A",IF(I35>=2022,Settings!$B$18,Settings!$B$19),IF(E35="B",Settings!$B$20,Settings!$B$21))+IF(F35="S",Settings!$B$22,0) | P35: =N35*O35 | Q35: =P35*INDEX(Settings!$B$25:$B$27,MATCH(F35,Settings!$A$25:$A$27,0)) | R35: Not contacted | S35: Approach with brochure (D40) | U35: Partner | V35: not assessed
A36: S167 | B36: Deloitte Legal | Telles | C36: Estruturação | D36: Todos os países · advogados em Portugal | E36: A | F36: L | G36: https://www.deloitte.com/pt/pt/services/legal/blogs/news/deloitte-legal-telles-band-1-private-wealth-law.html | H36: Band 1 in private wealth law. | I36: 2026 | J36: Search result, not opened | K36: Private wealth | L36: Website: deloitte.com/pt | M36: Journey checkpoint | N36: =INDEX(Settings!$B$4:$B$15,MATCH(M36,Settings!$A$4:$A$15,0)) | O36: =IF(E36="A",IF(I36>=2022,Settings!$B$18,Settings!$B$19),IF(E36="B",Settings!$B$20,Settings!$B$21))+IF(F36="S",Settings!$B$22,0) | P36: =N36*O36 | Q36: =P36*INDEX(Settings!$B$25:$B$27,MATCH(F36,Settings!$A$25:$A$27,0)) | R36: Not contacted | S36: Approach with brochure (D40) | U36: Partner | V36: not assessed
A37: S174 | B37: FRESH Legal | C37: Impostos nos EUA e em Portugal | D37: EUA | E37: A | F37: L | G37: https://fresh-legal.com/us | H37: Cross-border US tax planning and filing; Lisbon office and Portuguese legal practice. | I37: 2026 | J37: Opened | K37: Partners | L37: Website: fresh-legal.com | M37: Journey checkpoint | N37: =INDEX(Settings!$B$4:$B$15,MATCH(M37,Settings!$A$4:$A$15,0)) | O37: =IF(E37="A",IF(I37>=2022,Settings!$B$18,Settings!$B$19),IF(E37="B",Settings!$B$20,Settings!$B$21))+IF(F37="S",Settings!$B$22,0) | P37: =N37*O37 | Q37: =P37*INDEX(Settings!$B$25:$B$27,MATCH(F37,Settings!$A$25:$A$27,0)) | R37: Not contacted | S37: Approach with brochure (D40) | U37: Partner | V37: not assessed
A38: S172 | B38: Hagnéré Patrimoine | C38: Estruturação (×1.5) | D38: França | E38: A | F38: L | G38: https://www.hagnere-patrimoine.fr/gestion-de-patrimoine-expatrie-portugal | H38: Wealth adviser for French expatriates in Portugal: Franco-Portuguese tax, works with licensed Portuguese professionals. | I38: 2026 | J38: Opened | K38: Founding partner | L38: Website: hagnere-patrimoine.fr | M38: Journey checkpoint | N38: =INDEX(Settings!$B$4:$B$15,MATCH(M38,Settings!$A$4:$A$15,0)) | O38: =IF(E38="A",IF(I38>=2022,Settings!$B$18,Settings!$B$19),IF(E38="B",Settings!$B$20,Settings!$B$21))+IF(F38="S",Settings!$B$22,0) | P38: =N38*O38 | Q38: =P38*INDEX(Settings!$B$25:$B$27,MATCH(F38,Settings!$A$25:$A$27,0)) | R38: Not contacted | S38: Approach with brochure (D40) | U38: Partner | V38: not assessed
A39: S165 | B39: Julius Baer | C39: Estruturação (×1.5) | D39: Suíça | E39: A | F39: L | G39: https://www.essential-business.pt/2025/03/27/swiss-wealth-management-and-investment-bank-julius-baer-to-open-lisbon-office/ | H39: Opened a Lisbon office in 2025 for Portugal-linked wealth clients. | I39: 2026 | J39: Search result, not opened | K39: Head of Portugal desk | L39: Website: juliusbaer.com | M39: Journey checkpoint | N39: =INDEX(Settings!$B$4:$B$15,MATCH(M39,Settings!$A$4:$A$15,0)) | O39: =IF(E39="A",IF(I39>=2022,Settings!$B$18,Settings!$B$19),IF(E39="B",Settings!$B$20,Settings!$B$21))+IF(F39="S",Settings!$B$22,0) | P39: =N39*O39 | Q39: =P39*INDEX(Settings!$B$25:$B$27,MATCH(F39,Settings!$A$25:$A$27,0)) | R39: Not contacted | S39: Approach with brochure (D40) | U39: Partner | V39: not assessed
A40: S161 | B40: Krest | C40: Developer (Lisboa (Marvila)) | D40: LU, FR, CH, BR, US, IL | E40: A | F40: L | G40: https://www.essential-business.pt/2025/11/21/krest-unveils-formoso-marvila-residential-development-in-lisbon/ | H40: Formoso Marvila residential development unveiled in late 2025. | I40: 2026 | J40: Search result, not opened | K40: Marketing e vendas | L40: Website contact / LinkedIn | M40: Area placement (Strong) | N40: =INDEX(Settings!$B$4:$B$15,MATCH(M40,Settings!$A$4:$A$15,0)) | O40: =IF(E40="A",IF(I40>=2022,Settings!$B$18,Settings!$B$19),IF(E40="B",Settings!$B$20,Settings!$B$21))+IF(F40="S",Settings!$B$22,0) | P40: =N40*O40 | Q40: =P40*INDEX(Settings!$B$25:$B$27,MATCH(F40,Settings!$A$25:$A$27,0)) | R40: Not contacted | S40: Approach with brochure (D40) | U40: Partner | V40: not assessed
A41: S176 | B41: Taxbordr | C41: Impostos em Portugal (IFICI, não residentes) | D41: Todos os países · advogados em Portugal | E41: A | F41: L | G41: https://uk.trustpilot.com/review/taxbordr.com | H41: Portuguese tax advisers for international clients, rated on Trustpilot. | I41: 2026 | J41: Opened | K41: Founders | L41: Website: taxbordr.com | M41: Journey checkpoint | N41: =INDEX(Settings!$B$4:$B$15,MATCH(M41,Settings!$A$4:$A$15,0)) | O41: =IF(E41="A",IF(I41>=2022,Settings!$B$18,Settings!$B$19),IF(E41="B",Settings!$B$20,Settings!$B$21))+IF(F41="S",Settings!$B$22,0) | P41: =N41*O41 | Q41: =P41*INDEX(Settings!$B$25:$B$27,MATCH(F41,Settings!$A$25:$A$27,0)) | R41: Not contacted | S41: Approach with brochure (D40) | U41: Partner | V41: not assessed
... A44: S164 | B44: Yard Properties | C44: Developer (Madeira · Funchal) | D44: LU, FR, CH, BR, US, IL | E44: A | F44: L | G44: https://www.dnoticias.pt/2024/11/13/427070-yard-properties-investe-no-funchal-com-projecto-residencial-de-luxo/ | H44: Investing in a luxury residential project in Funchal. | I44: 2026 | J44: Search result, not opened | K44: Administração | L44: Website contact / LinkedIn | M44: Area placement (Strong) | N44: =INDEX(Settings!$B$4:$B$15,MATCH(M44,Settings!$A$4:$A$15,0)) | O44: =IF(E44="A",IF(I44>=2022,Settings!$B$18,Settings!$B$19),IF(E44="B",Settings!$B$20,Settings!$B$21))+IF(F44="S",Settings!$B$22,0) | P44: =N44*O44 | Q44: =P44*INDEX(Settings!$B$25:$B$27,MATCH(F44,Settings!$A$25:$A$27,0)) | R44: Not contacted | S44: Approach with brochure (D40) | U44: Partner | V44: not assessed
A45: S202 | B45: EFG Bank (Luxembourg), Lisbon office | C45: Private bank (private) | D45: LU, CH | E45: A | F45: L | G45: https://www.privatebankerinternational.com/news/efg-lisbon-portugal/ | H45: Wealth Partner tier (D33): Lisbon office as a branch of EFG Bank (Luxembourg) (prompt 15) | I45: 2019 | J45: Search result | K45: Head of international or Portugal desk | L45: LinkedIn (named role), then company email | M45: Wealth Partner | N45: =INDEX(Settings!$B$4:$B$15,MATCH(M45,Settings!$A$4:$A$15,0)) | O45: =IF(E45="A",IF(I45>=2022,Settings!$B$18,Settings!$B$19),IF(E45="B",Settings!$B$20,Settings!$B$21))+IF(F45="S",Settings!$B$22,0) | P45: =N45*O45 | Q45: =P45*INDEX(Settings!$B$25:$B$27,MATCH(F45,Settings!$A$25:$A$27,0)) | R45: To contact | S45: Touch 1 (sponsors/outreach/v3) | T45: 2026-11-09 | U45: Partner | V45: Switzerland
A46: S203 | B46: Lombard Odier | C46: Private bank (private) | D46: CH, BR | E46: A | F46: L | G46: https://www.finews.ch/news/banken/45646-lombard-odier-brasilien-sao-paulo-matteo-dignola | H46: Wealth Partner tier (D33): Brazil desk and São Paulo office; Portuguese-speaking team in Geneva (Portugal presence to confirm) (prompt 15) | I46: 2021 | J46: Search result | K46: Head of international or Portugal desk | L46: LinkedIn (named role), then company email | M46: Wealth Partner | N46: =INDEX(Settings!$B$4:$B$15,MATCH(M46,Settings!$A$4:$A$15,0)) | O46: =IF(E46="A",IF(I46>=2022,Settings!$B$18,Settings!$B$19),IF(E46="B",Settings!$B$20,Settings!$B$21))+IF(F46="S",Settings!$B$22,0) | P46: =N46*O46 | Q46: =P46*INDEX(Settings!$B$25:$B$27,MATCH(F46,Settings!$A$25:$A$27,0)) | R46: To contact | S46: Touch 1 (sponsors/outreach/v3) | T46: 2026-11-09 | U46: Partner | V46: Switzerland
A47: S001 | B47: ABANCA | C47: Bank | D47: CH | E47: A | F47: M | G47: https://www.abanca.pt/pt/residentes-suica/ | H47: Geneva branch with a dedicated contact for Portuguese residents; mortgages for homes in Portugal; CHF-to-Portugal transfers | I47: 2026 | J47: Fetched | K47: Marketing lead, non-resident / emigrant segment | L47: Website: abanca.pt | M47: Gold | N47: =INDEX(Settings!$B$4:$B$15,MATCH(M47,Settings!$A$4:$A$15,0)) | O47: =IF(E47="A",IF(I47>=2022,Settings!$B$18,Settings!$B$19),IF(E47="B",Settings!$B$20,Settings!$B$21))+IF(F47="S",Settings!$B$22,0) | P47: =N47*O47 | Q47: =P47*INDEX(Settings!$B$25:$B$27,MATCH(F47,Settings!$A$25:$A$27,0)) | R47: To contact | S47: Email 1 (template in sponsors/METHOD.md) + LinkedIn request on day 2 | T47: 2026-10-26 | U47: Partner | V47: not assessed
A48: S002 | B48: Banque BCP | C48: Bank | D48: FR | E48: A | F48: M | G48: https://lusojornal.com/salao-do-imobiliario-e-do-investimento-portugues-muda-se-para-a-porte-de-champeret/ | H48: Runs display ads on LusoJornal; sponsors community events (Lusopress 2023) | I48: 2024 | J48: Fetched | K48: Marketing lead, non-resident / emigrant segment | L48: Website: banquebcp.fr | M48: Gold | N48: =INDEX(Settings!$B$4:$B$15,MATCH(M48,Settings!$A$4:$A$15,0)) | O48: =IF(E48="A",IF(I48>=2022,Settings!$B$18,Settings!$B$19),IF(E48="B",Settings!$B$20,Settings!$B$21))+IF(F48="S",Settings!$B$22,0) | P48: =N48*O48 | Q48: =P48*INDEX(Settings!$B$25:$B$27,MATCH(F48,Settings!$A$25:$A$27,0)) | R48: To contact | S48: Email 1 (template in sponsors/METHOD.md) + LinkedIn request on day 2 | T48: 2026-10-26 | U48: Partner | V48: not assessed
A49: S003 | B49: Cabinet d'Architecture Marcelo Moledo | C49: Architecture | D49: FR | E49: A | F49: S | G49: https://lusopress.tv/wp-content/uploads/2023/07/lusopress_125.pdf | H49: Cover profile in Lusopress nº125; offices in Saint-Tropez and Viana do Castelo | I49: 2023 | J49: Fetched | K49: Owner or marketing lead | L49: Phone or email from company website, then LinkedIn | M49: Silver | N49: =INDEX(Settings!$B$4:$B$15,MATCH(M49,Settings!$A$4:$A$15,0)) | O49: =IF(E49="A",IF(I49>=2022,Settings!$B$18,Settings!$B$19),IF(E49="B",Settings!$B$20,Settings!$B$21))+IF(F49="S",Settings!$B$22,0) | P49: =N49*O49 | Q49: =P49*INDEX(Settings!$B$25:$B$27,MATCH(F49,Settings!$A$25:$A$27,0)) | R49: To contact | S49: Email 1 (template in sponsors/METHOD.md) + LinkedIn request on day 2 | T49: 2026-10-26 | U49: Partner | V49: not assessed
A50: S004 | B50: Campara (law firm) | C50: Law firm (Brazilian clients) | D50: BR | E50: A | F50: S | G50: https://www.eurodicas.com.br/conexao-europa-imoveis/ | H50: Promoted with referral-style links on Eurodicas | I50: 2026 | J50: Fetched | K50: Managing partner or business development | L50: Phone or email from company website, then LinkedIn | M50: Silver | N50: =INDEX(Settings!$B$4:$B$15,MATCH(M50,Settings!$A$4:$A$15,0)) | O50: =IF(E50="A",IF(I50>=2022,Settings!$B$18,Settings!$B$19),IF(E50="B",Settings!$B$20,Settings!$B$21))+IF(F50="S",Settings!$B$22,0) | P50: =N50*O50 | Q50: =P50*INDEX(Settings!$B$25:$B$27,MATCH(F50,Settings!$A$25:$A$27,0)) | R50: To contact | S50: Email 1 (template in sponsors/METHOD.md) + LinkedIn request on day 2 | T50: 2026-10-26 | U50: Partner | V50: not assessed
A51: S005 | B51: MC Avocats | C51: Law firm (France) | D51: FR | E51: A | F51: S | G51: https://lusojornal.com/salao-do-imobiliario-e-do-investimento-portugues-muda-se-para-a-porte-de-champeret/ | H51: Banner ad on LusoJornal | I51: 2024 | J51: Fetched | K51: Managing partner or business development | L51: Phone or email from company website, then LinkedIn | M51: Silver | N51: =INDEX(Settings!$B$4:$B$15,MATCH(M51,Settings!$A$4:$A$15,0)) | O51: =IF(E51="A",IF(I51>=2022,Settings!$B$18,Settings!$B$19),IF(E51="B",Settings!$B$20,Settings!$B$21))+IF(F51="S",Settings!$B$22,0) | P51: =N51*O51 | Q51: =P51*INDEX(Settings!$B$25:$B$27,MATCH(F51,Settings!$A$25:$A$27,0)) | R51: To contact | S51: Email 1 (template in sponsors/METHOD.md) + LinkedIn request on day 2 | T51: 2026-10-26 | U51: Partner | V51: not assessed
A52: S006 | B52: Madeira Estate | C52: Relocation / residency | D52: BR, FR | E52: A | F52: S | G52: https://www.dnoticias.pt/2022/12/21/340949-o-processo-de-abertura-de-uma-conta-bancaria-em-portugal/ | H52: Buys sponsored articles ('Patrocinado') in DNoticias | I52: 2022 | J52: Fetched | K52: Managing partner or business development | L52: Phone or email from company website, then LinkedIn | M52: Silver | N52: =INDEX(Settings!$B$4:$B$15,MATCH(M52,Settings!$A$4:$A$15,0)) | O52: =IF(E52="A",IF(I52>=2022,Settings!$B$18,Settings!$B$19),IF(E52="B",Settings!$B$20,Settings!$B$21))+IF(F52="S",Settings!$B$22,0) | P52: =N52*O52 | Q52: =P52*INDEX(Settings!$B$25:$B$27,MATCH(F52,Settings!$A$25:$A$27,0)) | R52: To contact | S52: Email 1 (template in sponsors/METHOD.md) + LinkedIn request on day 2 | T52: 2026-10-26 | U52: Partner | V52: not assessed
A53: S007 | B53: Pedro Emanuel de Oliveira (law office) | C53: Law firm | D53: FR | E53: A | F53: S | G53: https://lusopress.tv/wp-content/uploads/2023/07/lusopress_125.pdf | H53: Profile in Lusopress nº125; Bordeaux and Porto | I53: 2023 | J53: Fetched | K53: Managing partner or business development | L53: Phone or email from company website, then LinkedIn | M53: Silver | N53: =INDEX(Settings!$B$4:$B$15,MATCH(M53,Settings!$A$4:$A$15,0)) | O53: =IF(E53="A",IF(I53>=2022,Settings!$B$18,Settings!$B$19),IF(E53="B",Settings!$B$20,Settings!$B$21))+IF(F53="S",Settings!$B$22,0) | P53: =N53*O53 | Q53: =P53*INDEX(Settings!$B$25:$B$27,MATCH(F53,Settings!$A$25:$A$27,0)) | R53: To contact | S53: Email 1 (template in sponsors/METHOD.md) + LinkedIn request on day 2 | T53: 2026-10-26 | U53: Partner | V53: not assessed
A54: S008 | B54: Santander Totta | C54: Bank | D54: FR, LU, CH | E54: A | F54: L | G54: https://www.santander.pt/portugueses-residentes-exterior | H54: Dedicated offer for Portuguese living abroad incl. home loans for main or second home; sponsored a community festival in Lyon | I54: 2026 | J54: Fetched | K54: Marketing lead, non-resident / emigrant segment | L54: Website: santander.pt | M54: Gold | N54: =INDEX(Settings!$B$4:$B$15,MATCH(M54,Settings!$A$4:$A$15,0)) | O54: =IF(E54="A",IF(I54>=2022,Settings!$B$18,Settings!$B$19),IF(E54="B",Settings!$B$20,Settings!$B$21))+IF(F54="S",Settings!$B$22,0) | P54: =N54*O54 | Q54: =P54*INDEX(Settings!$B$25:$B$27,MATCH(F54,Settings!$A$25:$A$27,0)) | R54: To contact | S54: Email 1 (template in sponsors/METHOD.md) + LinkedIn request on day 2 | T54: 2026-10-26 | U54: Partner | V54: not assessed
A55: S009 | B55: Ebury | C55: FX (Brazil) | D55: BR | E55: B | F55: M | G55: https://br.ebury.com/blog/vou-comprar-um-imovel-em-portugal-e-agora-como-faco-o-pagamento | H55: Blog on paying for Portuguese property from Brazil | I55: 2026 | J55: Search result | K55: Partnerships / affiliates manager | L55: Website: ebury.com | M55: Gold | N55: =INDEX(Settings!$B$4:$B$15,MATCH(M55,Settings!$A$4:$A$15,0)) | O55: =IF(E55="A",IF(I55>=2022,Settings!$B$18,Settings!$B$19),IF(E55="B",Settings!$B$20,Settings!$B$21))+IF(F55="S",Settings!$B$22,0) | P55: =N55*O55 | Q55: =P55*INDEX(Settings!$B$25:$B$27,MATCH(F55,Settings!$A$25:$A$27,0)) | R55: To contact | S55: Email 1 (template in sponsors/METHOD.md) + LinkedIn request on day 2 | T55: 2026-10-27 | U55: Partner | V55: not assessed
A56: S010 | B56: Rio Credits | C56: Credit broker (France) | D56: FR | E56: A | F56: S | G56: https://lusopress.tv/wp-content/uploads/2018/12/10nomes10historias_3.pdf | H56: Featured in a Lusopress book; mortgages mainly for Portuguese clients in France. Check still active | I56: 2018 | J56: Fetched | K56: Partnerships or marketing lead | L56: Phone or email from company website, then LinkedIn | M56: Silver | N56: =INDEX(Settings!$B$4:$B$15,MATCH(M56,Settings!$A$4:$A$15,0)) | O56: =IF(E56="A",IF(I56>=2022,Settings!$B$18,Settings!$B$19),IF(E56="B",Settings!$B$20,Settings!$B$21))+IF(F56="S",Settings!$B$22,0) | P56: =N56*O56 | Q56: =P56*INDEX(Settings!$B$25:$B$27,MATCH(F56,Settings!$A$25:$A$27,0)) | R56: To contact | S56: Email 1 (template in sponsors/METHOD.md) + LinkedIn request on day 2 | T56: 2026-10-27 | U56: Partner | V56: not assessed
... A127: S070 | B127: Uniplaces | C127: Rentals | D127: BR | E127: B | F127: M | G127: https://www.uniplaces.com/city-explorer/aluguel-para-expatriados-em-portugal/ | H127: Brazilian-Portuguese guide for expats renting | I127: 2026 | J127: Search result | K127: Owner or marketing lead | L127: LinkedIn (named role), then company email | M127: Bronze | N127: =INDEX(Settings!$B$4:$B$15,MATCH(M127,Settings!$A$4:$A$15,0)) | O127: =IF(E127="A",IF(I127>=2022,Settings!$B$18,Settings!$B$19),IF(E127="B",Settings!$B$20,Settings!$B$21))+IF(F127="S",Settings!$B$22,0) | P127: =N127*O127 | Q127: =P127*INDEX(Settings!$B$25:$B$27,MATCH(F127,Settings!$A$25:$A$27,0)) | R127: To contact | S127: Email 1 + LinkedIn request on day 2 | T127: 2026-11-04 | U127: Partner | V127: not assessed
A128: S075 | B128: Antas da Cunha Ecija | C128: Law firm | D128: LU, FR, CH, BR | E128: A | F128: L | H128: Large or generic; no proof of spend on our audience | K128: Managing partner or business development | L128: Website: ecija.com | M128: Silver | N128: =INDEX(Settings!$B$4:$B$15,MATCH(M128,Settings!$A$4:$A$15,0)) | O128: =IF(E128="A",IF(I128>=2022,Settings!$B$18,Settings!$B$19),IF(E128="B",Settings!$B$20,Settings!$B$21))+IF(F128="S",Settings!$B$22,0) | P128: =N128*O128 | Q128: =P128*INDEX(Settings!$B$25:$B$27,MATCH(F128,Settings!$A$25:$A$27,0)) | R128: Parked | S128: Approach with brochure (D40) | T128: 2026-12-01 | U128: CEO | V128: not assessed
A129: S077 | B129: Avenue | C129: Developer | D129: LU, FR, CH, BR | E129: A | F129: L | H129: Large or generic; no proof of spend on our audience | K129: Sales or marketing director | L129: LinkedIn (named role); general partnerships email as backup | M129: Silver | N129: =INDEX(Settings!$B$4:$B$15,MATCH(M129,Settings!$A$4:$A$15,0)) | O129: =IF(E129="A",IF(I129>=2022,Settings!$B$18,Settings!$B$19),IF(E129="B",Settings!$B$20,Settings!$B$21))+IF(F129="S",Settings!$B$22,0) | P129: =N129*O129 | Q129: =P129*INDEX(Settings!$B$25:$B$27,MATCH(F129,Settings!$A$25:$A$27,0)) | R129: Parked | S129: Approach with brochure (D40) | T129: 2026-12-01 | U129: CEO | V129: not assessed
A130: S086 | B130: Currencies Direct | C130: FX | D130: LU, FR, CH, BR | E130: A | F130: L | H130: Large or generic; no proof of spend on our audience | K130: Partnerships / affiliates manager | L130: Website: currenciesdirect.com | M130: Silver | N130: =INDEX(Settings!$B$4:$B$15,MATCH(M130,Settings!$A$4:$A$15,0)) | O130: =IF(E130="A",IF(I130>=2022,Settings!$B$18,Settings!$B$19),IF(E130="B",Settings!$B$20,Settings!$B$21))+IF(F130="S",Settings!$B$22,0) | P130: =N130*O130 | Q130: =P130*INDEX(Settings!$B$25:$B$27,MATCH(F130,Settings!$A$25:$A$27,0)) | R130: Parked | S130: Approach with brochure (D40) | T130: 2026-12-01 | U130: CEO | V130: not assessed
A131: S121 | B131: VIC Properties | C131: Developer | D131: LU, FR, CH, BR | E131: A | F131: L | H131: Large or generic; no proof of spend on our audience | K131: Sales or marketing director | L131: Website: vic-properties.com | M131: Silver | N131: =INDEX(Settings!$B$4:$B$15,MATCH(M131,Settings!$A$4:$A$15,0)) | O131: =IF(E131="A",IF(I131>=2022,Settings!$B$18,Settings!$B$19),IF(E131="B",Settings!$B$20,Settings!$B$21))+IF(F131="S",Settings!$B$22,0) | P131: =N131*O131 | Q131: =P131*INDEX(Settings!$B$25:$B$27,MATCH(F131,Settings!$A$25:$A$27,0)) | R131: Parked | S131: Approach with brochure (D40) | T131: 2026-12-01 | U131: CEO | V131: not assessed
A132: S123 | B132: Vanguard Properties | C132: Developer | D132: LU, FR, CH, BR | E132: A | F132: L | H132: Large or generic; no proof of spend on our audience | K132: Sales or marketing director | L132: Website: vangproperties.com | M132: Silver | N132: =INDEX(Settings!$B$4:$B$15,MATCH(M132,Settings!$A$4:$A$15,0)) | O132: =IF(E132="A",IF(I132>=2022,Settings!$B$18,Settings!$B$19),IF(E132="B",Settings!$B$20,Settings!$B$21))+IF(F132="S",Settings!$B$22,0) | P132: =N132*O132 | Q132: =P132*INDEX(Settings!$B$25:$B$27,MATCH(F132,Settings!$A$25:$A$27,0)) | R132: Parked | S132: Approach with brochure (D40) | T132: 2026-12-01 | U132: CEO | V132: not assessed

Sheet Later (tier C)
A1: ID | B1: Company | C1: Sector | D1: Editions | E1: Tier | F1: Size | G1: Evidence URL | H1: Evidence | I1: Evidence year | J1: Evidence check | K1: Who to reach | L1: Channel | M1: Offer | N1: Deal value year 1 (€) | O1: Close probability | P1: Expected value (€) | Q1: Priority score | R1: Status | S1: Next action | T1: Next action date | U1: Owner | V1: Capital origin
A2: S071 | B2: AGS Four Winds | C2: Moving | D2: LU, FR, CH, BR | E2: C | F2: L | H2: Large or generic; no proof of spend on our audience | K2: Owner or marketing lead | L2: LinkedIn (named role); general partnerships email as backup | M2: Silver | N2: =INDEX(Settings!$B$4:$B$15,MATCH(M2,Settings!$A$4:$A$15,0)) | O2: =IF(E2="A",IF(I2>=2022,Settings!$B$18,Settings!$B$19),IF(E2="B",Settings!$B$20,Settings!$B$21))+IF(F2="S",Settings!$B$22,0) | P2: =N2*O2 | Q2: =P2*INDEX(Settings!$B$25:$B$27,MATCH(F2,Settings!$A$25:$A$27,0)) | R2: Parked | S2: Revisit when 1,000 subscribers or a warm intro exists | T2: 2026-12-01 | U2: CEO | V2: not assessed
A3: S150 | B3: ARAG | C3: Insurance | D3: LU, FR, CH, BR, US, IL | E3: C | F3: L | G3: https://www.doutorfinancas.pt/seguro-vida-geral/ | H3: Insurer listed as a partner by Doutor Finanças' insurance intermediary (Doutor Finanças Protege) (prompt 13); no proof of spend on our audience | I3: 2026 | J3: Fetched | K3: Marketing lead, intermediary / partnerships | L3: LinkedIn (named role); general partnerships email as backup | M3: Silver | N3: =INDEX(Settings!$B$4:$B$15,MATCH(M3,Settings!$A$4:$A$15,0)) | O3: =IF(E3="A",IF(I3>=2022,Settings!$B$18,Settings!$B$19),IF(E3="B",Settings!$B$20,Settings!$B$21))+IF(F3="S",Settings!$B$22,0) | P3: =N3*O3 | Q3: =P3*INDEX(Settings!$B$25:$B$27,MATCH(F3,Settings!$A$25:$A$27,0)) | R3: Parked | S3: Revisit when 1,000 subscribers or a warm intro exists | T3: 2026-12-01 | U3: CEO | V3: not assessed
A4: S072 | B4: Allianz Portugal | C4: Insurance | D4: LU, FR, CH, BR | E4: C | F4: L | H4: Large or generic; no proof of spend on our audience | K4: Marketing lead, retail | L4: LinkedIn (named role); general partnerships email as backup | M4: Silver | N4: =INDEX(Settings!$B$4:$B$15,MATCH(M4,Settings!$A$4:$A$15,0)) | O4: =IF(E4="A",IF(I4>=2022,Settings!$B$18,Settings!$B$19),IF(E4="B",Settings!$B$20,Settings!$B$21))+IF(F4="S",Settings!$B$22,0) | P4: =N4*O4 | Q4: =P4*INDEX(Settings!$B$25:$B$27,MATCH(F4,Settings!$A$25:$A$27,0)) | R4: Parked | S4: Revisit when 1,000 subscribers or a warm intro exists | T4: 2026-12-01 | U4: CEO | V4: not assessed
A5: S073 | B5: Allied Pickfords | C5: Moving | D5: LU, FR, CH, BR | E5: C | F5: L | H5: Large or generic; no proof of spend on our audience | K5: Owner or marketing lead | L5: LinkedIn (named role); general partnerships email as backup | M5: Silver | N5: =INDEX(Settings!$B$4:$B$15,MATCH(M5,Settings!$A$4:$A$15,0)) | O5: =IF(E5="A",IF(I5>=2022,Settings!$B$18,Settings!$B$19),IF(E5="B",Settings!$B$20,Settings!$B$21))+IF(F5="S",Settings!$B$22,0) | P5: =N5*O5 | Q5: =P5*INDEX(Settings!$B$25:$B$27,MATCH(F5,Settings!$A$25:$A$27,0)) | R5: Parked | S5: Revisit when 1,000 subscribers or a warm intro exists | T5: 2026-12-01 | U5: CEO | V5: not assessed
A6: S074 | B6: Altido | C6: Rental management | D6: LU, FR, CH, BR | E6: C | F6: L | H6: Large or generic; no proof of spend on our audience | K6: Owner or marketing lead | L6: LinkedIn (named role); general partnerships email as backup | M6: Silver | N6: =INDEX(Settings!$B$4:$B$15,MATCH(M6,Settings!$A$4:$A$15,0)) | O6: =IF(E6="A",IF(I6>=2022,Settings!$B$18,Settings!$B$19),IF(E6="B",Settings!$B$20,Settings!$B$21))+IF(F6="S",Settings!$B$22,0) | P6: =N6*O6 | Q6: =P6*INDEX(Settings!$B$25:$B$27,MATCH(F6,Settings!$A$25:$A$27,0)) | R6: Parked | S6: Revisit when 1,000 subscribers or a warm intro exists | T6: 2026-12-01 | U6: CEO | V6: not assessed
A7: S144 | B7: April Portugal | C7: Insurance | D7: LU, FR, CH, BR, US, IL | E7: C | F7: L | G7: https://www.doutorfinancas.pt/seguro-vida-geral/ | H7: Insurer listed as a partner by Doutor Finanças' insurance intermediary (Doutor Finanças Protege) (prompt 13); no proof of spend on our audience | I7: 2026 | J7: Fetched | K7: Marketing lead, intermediary / partnerships | L7: LinkedIn (named role); general partnerships email as backup | M7: Silver | N7: =INDEX(Settings!$B$4:$B$15,MATCH(M7,Settings!$A$4:$A$15,0)) | O7: =IF(E7="A",IF(I7>=2022,Settings!$B$18,Settings!$B$19),IF(E7="B",Settings!$B$20,Settings!$B$21))+IF(F7="S",Settings!$B$22,0) | P7: =N7*O7 | Q7: =P7*INDEX(Settings!$B$25:$B$27,MATCH(F7,Settings!$A$25:$A$27,0)) | R7: Parked | S7: Revisit when 1,000 subscribers or a warm intro exists | T7: 2026-12-01 | U7: CEO | V7: not assessed
A8: S146 | B8: Asisa | C8: Insurance | D8: LU, FR, CH, BR, US, IL | E8: C | F8: L | G8: https://www.doutorfinancas.pt/seguro-vida-geral/ | H8: Insurer listed as a partner by Doutor Finanças' insurance intermediary (Doutor Finanças Protege) (prompt 13); no proof of spend on our audience | I8: 2026 | J8: Fetched | K8: Marketing lead, intermediary / partnerships | L8: LinkedIn (named role); general partnerships email as backup | M8: Silver | N8: =INDEX(Settings!$B$4:$B$15,MATCH(M8,Settings!$A$4:$A$15,0)) | O8: =IF(E8="A",IF(I8>=2022,Settings!$B$18,Settings!$B$19),IF(E8="B",Settings!$B$20,Settings!$B$21))+IF(F8="S",Settings!$B$22,0) | P8: =N8*O8 | Q8: =P8*INDEX(Settings!$B$25:$B$27,MATCH(F8,Settings!$A$25:$A$27,0)) | R8: Parked | S8: Revisit when 1,000 subscribers or a warm intro exists | T8: 2026-12-01 | U8: CEO | V8: not assessed
A9: S076 | B9: Atlantic Bridge | C9: Relocation (Brazil) | D9: BR | E9: C | F9: L | H9: Large or generic; no proof of spend on our audience | K9: Owner or marketing lead | L9: LinkedIn (named role); general partnerships email as backup | M9: Silver | N9: =INDEX(Settings!$B$4:$B$15,MATCH(M9,Settings!$A$4:$A$15,0)) | O9: =IF(E9="A",IF(I9>=2022,Settings!$B$18,Settings!$B$19),IF(E9="B",Settings!$B$20,Settings!$B$21))+IF(F9="S",Settings!$B$22,0) | P9: =N9*O9 | Q9: =P9*INDEX(Settings!$B$25:$B$27,MATCH(F9,Settings!$A$25:$A$27,0)) | R9: Parked | S9: Revisit when 1,000 subscribers or a warm intro exists | T9: 2026-12-01 | U9: CEO | V9: not assessed
A10: S078 | B10: BGL BNP Paribas | C10: Bank (Luxembourg) | D10: LU | E10: C | F10: L | H10: Large or generic; no proof of spend on our audience | K10: Marketing lead, non-resident / emigrant segment | L10: LinkedIn (named role); general partnerships email as backup | M10: Gold | N10: =INDEX(Settings!$B$4:$B$15,MATCH(M10,Settings!$A$4:$A$15,0)) | O10: =IF(E10="A",IF(I10>=2022,Settings!$B$18,Settings!$B$19),IF(E10="B",Settings!$B$20,Settings!$B$21))+IF(F10="S",Settings!$B$22,0) | P10: =N10*O10 | Q10: =P10*INDEX(Settings!$B$25:$B$27,MATCH(F10,Settings!$A$25:$A$27,0)) | R10: Parked | S10: Revisit when 1,000 subscribers or a warm intro exists | T10: 2026-12-01 | U10: CEO | V10: not assessed
A11: S079 | B11: Banco Inter | C11: Bank (Brazil) | D11: BR | E11: C | F11: L | H11: Large or generic; no proof of spend on our audience | K11: Marketing lead, non-resident / emigrant segment | L11: LinkedIn (named role); general partnerships email as backup | M11: Gold | N11: =INDEX(Settings!$B$4:$B$15,MATCH(M11,Settings!$A$4:$A$15,0)) | O11: =IF(E11="A",IF(I11>=2022,Settings!$B$18,Settings!$B$19),IF(E11="B",Settings!$B$20,Settings!$B$21))+IF(F11="S",Settings!$B$22,0) | P11: =N11*O11 | Q11: =P11*INDEX(Settings!$B$25:$B$27,MATCH(F11,Settings!$A$25:$A$27,0)) | R11: Parked | S11: Revisit when 1,000 subscribers or a warm intro exists | T11: 2026-12-01 | U11: CEO | V11: not assessed
A12: S080 | B12: Banco do Brasil (Portugal) | C12: Bank | D12: LU, FR, CH, BR | E12: C | F12: L | H12: Large or generic; no proof of spend on our audience | K12: Marketing lead, non-resident / emigrant segment | L12: LinkedIn (named role); general partnerships email as backup | M12: Gold | N12: =INDEX(Settings!$B$4:$B$15,MATCH(M12,Settings!$A$4:$A$15,0)) | O12: =IF(E12="A",IF(I12>=2022,Settings!$B$18,Settings!$B$19),IF(E12="B",Settings!$B$20,Settings!$B$21))+IF(F12="S",Settings!$B$22,0) | P12: =N12*O12 | Q12: =P12*INDEX(Settings!$B$25:$B$27,MATCH(F12,Settings!$A$25:$A$27,0)) | R12: Parked | S12: Revisit when 1,000 subscribers or a warm intro exists | T12: 2026-12-01 | U12: CEO | V12: not assessed
A13: S081 | B13: Bankinter Portugal | C13: Bank | D13: LU, FR, CH, BR | E13: C | F13: L | H13: Large or generic; no proof of spend on our audience | K13: Marketing lead, non-resident / emigrant segment | L13: LinkedIn (named role); general partnerships email as backup | M13: Gold | N13: =INDEX(Settings!$B$4:$B$15,MATCH(M13,Settings!$A$4:$A$15,0)) | O13: =IF(E13="A",IF(I13>=2022,Settings!$B$18,Settings!$B$19),IF(E13="B",Settings!$B$20,Settings!$B$21))+IF(F13="S",Settings!$B$22,0) | P13: =N13*O13 | Q13: =P13*INDEX(Settings!$B$25:$B$27,MATCH(F13,Settings!$A$25:$A$27,0)) | R13: Parked | S13: Revisit when 1,000 subscribers or a warm intro exists | T13: 2026-12-01 | U13: CEO | V13: not assessed
A14: S082 | B14: Banque Raiffeisen | C14: Bank (Luxembourg) | D14: LU | E14: C | F14: L | H14: Large or generic; no proof of spend on our audience | K14: Marketing lead, non-resident / emigrant segment | L14: LinkedIn (named role); general partnerships email as backup | M14: Gold | N14: =INDEX(Settings!$B$4:$B$15,MATCH(M14,Settings!$A$4:$A$15,0)) | O14: =IF(E14="A",IF(I14>=2022,Settings!$B$18,Settings!$B$19),IF(E14="B",Settings!$B$20,Settings!$B$21))+IF(F14="S",Settings!$B$22,0) | P14: =N14*O14 | Q14: =P14*INDEX(Settings!$B$25:$B$27,MATCH(F14,Settings!$A$25:$A$27,0)) | R14: Parked | S14: Revisit when 1,000 subscribers or a warm intro exists | T14: 2026-12-01 | U14: CEO | V14: not assessed
A15: S147 | B15: Bupa (Portugal) | C15: Insurance | D15: LU, FR, CH, BR, US, IL | E15: C | F15: L | G15: https://www.doutorfinancas.pt/seguro-vida-geral/ | H15: Insurer listed as a partner by Doutor Finanças' insurance intermediary (Doutor Finanças Protege) (prompt 13); no proof of spend on our audience | I15: 2026 | J15: Fetched | K15: Marketing lead, intermediary / partnerships | L15: LinkedIn (named role); general partnerships email as backup | M15: Silver | N15: =INDEX(Settings!$B$4:$B$15,MATCH(M15,Settings!$A$4:$A$15,0)) | O15: =IF(E15="A",IF(I15>=2022,Settings!$B$18,Settings!$B$19),IF(E15="B",Settings!$B$20,Settings!$B$21))+IF(F15="S",Settings!$B$22,0) | P15: =N15*O15 | Q15: =P15*INDEX(Settings!$B$25:$B$27,MATCH(F15,Settings!$A$25:$A$27,0)) | R15: Parked | S15: Revisit when 1,000 subscribers or a warm intro exists | T15: 2026-12-01 | U15: CEO | V15: not assessed
A16: S083 | B16: C6 Bank | C16: Bank (Brazil) | D16: BR | E16: C | F16: L | H16: Large or generic; no proof of spend on our audience | K16: Marketing lead, non-resident / emigrant segment | L16: LinkedIn (named role); general partnerships email as backup | M16: Gold | N16: =INDEX(Settings!$B$4:$B$15,MATCH(M16,Settings!$A$4:$A$15,0)) | O16: =IF(E16="A",IF(I16>=2022,Settings!$B$18,Settings!$B$19),IF(E16="B",Settings!$B$20,Settings!$B$21))+IF(F16="S",Settings!$B$22,0) | P16: =N16*O16 | Q16: =P16*INDEX(Settings!$B$25:$B$27,MATCH(F16,Settings!$A$25:$A$27,0)) | R16: Parked | S16: Revisit when 1,000 subscribers or a warm intro exists | T16: 2026-12-01 | U16: CEO | V16: not assessed
A17: S084 | B17: Caiado Guerreiro | C17: Law firm | D17: LU, FR, CH, BR | E17: C | F17: L | H17: Large or generic; no proof of spend on our audience | K17: Managing partner or business development | L17: LinkedIn (named role); general partnerships email as backup | M17: Silver | N17: =INDEX(Settings!$B$4:$B$15,MATCH(M17,Settings!$A$4:$A$15,0)) | O17: =IF(E17="A",IF(I17>=2022,Settings!$B$18,Settings!$B$19),IF(E17="B",Settings!$B$20,Settings!$B$21))+IF(F17="S",Settings!$B$22,0) | P17: =N17*O17 | Q17: =P17*INDEX(Settings!$B$25:$B$27,MATCH(F17,Settings!$A$25:$A$27,0)) | R17: Parked | S17: Revisit when 1,000 subscribers or a warm intro exists | T17: 2026-12-01 | U17: CEO | V17: not assessed
A18: S141 | B18: Caravela Seguros | C18: Insurance | D18: LU, FR, CH, BR, US, IL | E18: C | F18: L | G18: https://www.doutorfinancas.pt/seguro-vida-geral/ | H18: Insurer listed as a partner by Doutor Finanças' insurance intermediary (Doutor Finanças Protege) (prompt 13); no proof of spend on our audience | I18: 2026 | J18: Fetched | K18: Marketing lead, intermediary / partnerships | L18: LinkedIn (named role); general partnerships email as backup | M18: Silver | N18: =INDEX(Settings!$B$4:$B$15,MATCH(M18,Settings!$A$4:$A$15,0)) | O18: =IF(E18="A",IF(I18>=2022,Settings!$B$18,Settings!$B$19),IF(E18="B",Settings!$B$20,Settings!$B$21))+IF(F18="S",Settings!$B$22,0) | P18: =N18*O18 | Q18: =P18*INDEX(Settings!$B$25:$B$27,MATCH(F18,Settings!$A$25:$A$27,0)) | R18: Parked | S18: Revisit when 1,000 subscribers or a warm intro exists | T18: 2026-12-01 | U18: CEO | V18: not assessed
A19: S085 | B19: Cidadania4u | C19: Citizenship services | D19: LU, FR, CH, BR | E19: C | F19: L | H19: Large or generic; no proof of spend on our audience | K19: Owner or marketing lead | L19: LinkedIn (named role); general partnerships email as backup | M19: Silver | N19: =INDEX(Settings!$B$4:$B$15,MATCH(M19,Settings!$A$4:$A$15,0)) | O19: =IF(E19="A",IF(I19>=2022,Settings!$B$18,Settings!$B$19),IF(E19="B",Settings!$B$20,Settings!$B$21))+IF(F19="S",Settings!$B$22,0) | P19: =N19*O19 | Q19: =P19*INDEX(Settings!$B$25:$B$27,MATCH(F19,Settings!$A$25:$A$27,0)) | R19: Parked | S19: Revisit when 1,000 subscribers or a warm intro exists | T19: 2026-12-01 | U19: CEO | V19: not assessed
A20: S087 | B20: Decisões e Soluções | C20: Credit / real estate network | D20: LU, FR, CH, BR | E20: C | F20: L | H20: Large or generic; no proof of spend on our audience | K20: Partnerships or marketing lead | L20: LinkedIn (named role); general partnerships email as backup | M20: Silver | N20: =INDEX(Settings!$B$4:$B$15,MATCH(M20,Settings!$A$4:$A$15,0)) | O20: =IF(E20="A",IF(I20>=2022,Settings!$B$18,Settings!$B$19),IF(E20="B",Settings!$B$20,Settings!$B$21))+IF(F20="S",Settings!$B$22,0) | P20: =N20*O20 | Q20: =P20*INDEX(Settings!$B$25:$B$27,MATCH(F20,Settings!$A$25:$A$27,0)) | R20: Parked | S20: Revisit when 1,000 subscribers or a warm intro exists | T20: 2026-12-01 | U20: CEO | V20: not assessed
A21: S088 | B21: EDP Comercial | C21: Energy / solar | D21: LU, FR, CH, BR | E21: C | F21: L | H21: Large or generic; no proof of spend on our audience | K21: Owner or marketing lead | L21: LinkedIn (named role); general partnerships email as backup | M21: Silver | N21: =INDEX(Settings!$B$4:$B$15,MATCH(M21,Settings!$A$4:$A$15,0)) | O21: =IF(E21="A",IF(I21>=2022,Settings!$B$18,Settings!$B$19),IF(E21="B",Settings!$B$20,Settings!$B$21))+IF(F21="S",Settings!$B$22,0) | P21: =N21*O21 | Q21: =P21*INDEX(Settings!$B$25:$B$27,MATCH(F21,Settings!$A$25:$A$27,0)) | R21: Parked | S21: Revisit when 1,000 subscribers or a warm intro exists | T21: 2026-12-01 | U21: CEO | V21: not assessed
A22: S089 | B22: Empruntis | C22: Credit broker (France) | D22: FR | E22: C | F22: L | H22: Large or generic; no proof of spend on our audience | K22: Partnerships or marketing lead | L22: LinkedIn (named role); general partnerships email as backup | M22: Silver | N22: =INDEX(Settings!$B$4:$B$15,MATCH(M22,Settings!$A$4:$A$15,0)) | O22: =IF(E22="A",IF(I22>=2022,Settings!$B$18,Settings!$B$19),IF(E22="B",Settings!$B$20,Settings!$B$21))+IF(F22="S",Settings!$B$22,0) | P22: =N22*O22 | Q22: =P22*INDEX(Settings!$B$25:$B$27,MATCH(F22,Settings!$A$25:$A$27,0)) | R22: Parked | S22: Revisit when 1,000 subscribers or a warm intro exists | T22: 2026-12-01 | U22: CEO | V22: not assessed
A23: S145 | B23: Europ Assistance | C23: Insurance | D23: LU, FR, CH, BR, US, IL | E23: C | F23: L | G23: https://www.doutorfinancas.pt/seguro-vida-geral/ | H23: Insurer listed as a partner by Doutor Finanças' insurance intermediary (Doutor Finanças Protege) (prompt 13); no proof of spend on our audience | I23: 2026 | J23: Fetched | K23: Marketing lead, intermediary / partnerships | L23: LinkedIn (named role); general partnerships email as backup | M23: Silver | N23: =INDEX(Settings!$B$4:$B$15,MATCH(M23,Settings!$A$4:$A$15,0)) | O23: =IF(E23="A",IF(I23>=2022,Settings!$B$18,Settings!$B$19),IF(E23="B",Settings!$B$20,Settings!$B$21))+IF(F23="S",Settings!$B$22,0) | P23: =N23*O23 | Q23: =P23*INDEX(Settings!$B$25:$B$27,MATCH(F23,Settings!$A$25:$A$27,0)) | R23: Parked | S23: Revisit when 1,000 subscribers or a warm intro exists | T23: 2026-12-01 | U23: CEO | V23: not assessed
A24: S090 | B24: Feels Like Home | C24: Rental management | D24: LU, FR, CH, BR | E24: C | F24: L | H24: Large or generic; no proof of spend on our audience | K24: Owner or marketing lead | L24: LinkedIn (named role); general partnerships email as backup | M24: Silver | N24: =INDEX(Settings!$B$4:$B$15,MATCH(M24,Settings!$A$4:$A$15,0)) | O24: =IF(E24="A",IF(I24>=2022,Settings!$B$18,Settings!$B$19),IF(E24="B",Settings!$B$20,Settings!$B$21))+IF(F24="S",Settings!$B$22,0) | P24: =N24*O24 | Q24: =P24*INDEX(Settings!$B$25:$B$27,MATCH(F24,Settings!$A$25:$A$27,0)) | R24: Parked | S24: Revisit when 1,000 subscribers or a warm intro exists | T24: 2026-12-01 | U24: CEO | V24: not assessed
A25: S091 | B25: Fixando | C25: Services marketplace | D25: LU, FR, CH, BR | E25: C | F25: L | H25: Large or generic; no proof of spend on our audience | K25: Owner or marketing lead | L25: LinkedIn (named role); general partnerships email as backup | M25: Silver | N25: =INDEX(Settings!$B$4:$B$15,MATCH(M25,Settings!$A$4:$A$15,0)) | O25: =IF(E25="A",IF(I25>=2022,Settings!$B$18,Settings!$B$19),IF(E25="B",Settings!$B$20,Settings!$B$21))+IF(F25="S",Settings!$B$22,0) | P25: =N25*O25 | Q25: =P25*INDEX(Settings!$B$25:$B$27,MATCH(F25,Settings!$A$25:$A$27,0)) | R25: Parked | S25: Revisit when 1,000 subscribers or a warm intro exists | T25: 2026-12-01 | U25: CEO | V25: not assessed
A26: S154 | B26: Fortera | C26: Developer | D26: IL, US | E26: C | F26: L | G26: https://www.essential-business.pt/?p=16891 | H26: Israeli developer; 500 M€ plan for about 1,000 homes in Greater Porto (Mar 2022), Skyline tower in Gaia. No evidence of marketing to foreign buyers, and it advertises an average 24% yield to investors, which our editorial policy does not let us repeat | I26: 2022 | J26: Fetched | K26: Sales or marketing director | L26: LinkedIn (named role); general partnerships email as backup | M26: Campaign | N26: =INDEX(Settings!$B$4:$B$15,MATCH(M26,Settings!$A$4:$A$15,0)) | O26: =IF(E26="A",IF(I26>=2022,Settings!$B$18,Settings!$B$19),IF(E26="B",Settings!$B$20,Settings!$B$21))+IF(F26="S",Settings!$B$22,0) | P26: =N26*O26 | Q26: =P26*INDEX(Settings!$B$25:$B$27,MATCH(F26,Settings!$A$25:$A$27,0)) | R26: Parked | S26: Revisit when 1,000 subscribers or a warm intro exists | T26: 2026-12-01 | U26: CEO | V26: Israel
A27: S092 | B27: Foyer | C27: Insurance (Luxembourg) | D27: LU | E27: C | F27: L | H27: Large or generic; no proof of spend on our audience | K27: Marketing lead, retail | L27: LinkedIn (named role); general partnerships email as backup | M27: Silver | N27: =INDEX(Settings!$B$4:$B$15,MATCH(M27,Settings!$A$4:$A$15,0)) | O27: =IF(E27="A",IF(I27>=2022,Settings!$B$18,Settings!$B$19),IF(E27="B",Settings!$B$20,Settings!$B$21))+IF(F27="S",Settings!$B$22,0) | P27: =N27*O27 | Q27: =P27*INDEX(Settings!$B$25:$B$27,MATCH(F27,Settings!$A$25:$A$27,0)) | R27: Parked | S27: Revisit when 1,000 subscribers or a warm intro exists | T27: 2026-12-01 | U27: CEO | V27: not assessed
A28: S093 | B28: Galp Solar | C28: Solar | D28: LU, FR, CH, BR | E28: C | F28: L | H28: Large or generic; no proof of spend on our audience | K28: Owner or marketing lead | L28: LinkedIn (named role); general partnerships email as backup | M28: Silver | N28: =INDEX(Settings!$B$4:$B$15,MATCH(M28,Settings!$A$4:$A$15,0)) | O28: =IF(E28="A",IF(I28>=2022,Settings!$B$18,Settings!$B$19),IF(E28="B",Settings!$B$20,Settings!$B$21))+IF(F28="S",Settings!$B$22,0) | P28: =N28*O28 | Q28: =P28*INDEX(Settings!$B$25:$B$27,MATCH(F28,Settings!$A$25:$A$27,0)) | R28: Parked | S28: Revisit when 1,000 subscribers or a warm intro exists | T28: 2026-12-01 | U28: CEO | V28: not assessed
A29: S094 | B29: Generali Tranquilidade | C29: Insurance | D29: LU, FR, CH, BR | E29: C | F29: L | H29: Large or generic; no proof of spend on our audience | K29: Marketing lead, retail | L29: LinkedIn (named role); general partnerships email as backup | M29: Silver | N29: =INDEX(Settings!$B$4:$B$15,MATCH(M29,Settings!$A$4:$A$15,0)) | O29: =IF(E29="A",IF(I29>=2022,Settings!$B$18,Settings!$B$19),IF(E29="B",Settings!$B$20,Settings!$B$21))+IF(F29="S",Settings!$B$22,0) | P29: =N29*O29 | Q29: =P29*INDEX(Settings!$B$25:$B$27,MATCH(F29,Settings!$A$25:$A$27,0)) | R29: Parked | S29: Revisit when 1,000 subscribers or a warm intro exists | T29: 2026-12-01 | U29: CEO | V29: not assessed
A30: S095 | B30: Global Citizen Solutions | C30: Residency advisory | D30: LU, FR, CH, BR | E30: C | F30: L | H30: Large or generic; no proof of spend on our audience | K30: Managing partner or business development | L30: LinkedIn (named role); general partnerships email as backup | M30: Silver | N30: =INDEX(Settings!$B$4:$B$15,MATCH(M30,Settings!$A$4:$A$15,0)) | O30: =IF(E30="A",IF(I30>=2022,Settings!$B$18,Settings!$B$19),IF(E30="B",Settings!$B$20,Settings!$B$21))+IF(F30="S",Settings!$B$22,0) | P30: =N30*O30 | Q30: =P30*INDEX(Settings!$B$25:$B$27,MATCH(F30,Settings!$A$25:$A$27,0)) | R30: Parked | S30: Revisit when 1,000 subscribers or a warm intro exists | T30: 2026-12-01 | U30: CEO | V30: not assessed
A31: S142 | B31: Habit Seguros | C31: Insurance | D31: LU, FR, CH, BR, US, IL | E31: C | F31: L | G31: https://www.doutorfinancas.pt/seguro-vida-geral/ | H31: Insurer listed as a partner by Doutor Finanças' insurance intermediary (Doutor Finanças Protege) (prompt 13); no proof of spend on our audience | I31: 2026 | J31: Fetched | K31: Marketing lead, intermediary / partnerships | L31: LinkedIn (named role); general partnerships email as backup | M31: Silver | N31: =INDEX(Settings!$B$4:$B$15,MATCH(M31,Settings!$A$4:$A$15,0)) | O31: =IF(E31="A",IF(I31>=2022,Settings!$B$18,Settings!$B$19),IF(E31="B",Settings!$B$20,Settings!$B$21))+IF(F31="S",Settings!$B$22,0) | P31: =N31*O31 | Q31: =P31*INDEX(Settings!$B$25:$B$27,MATCH(F31,Settings!$A$25:$A$27,0)) | R31: Parked | S31: Revisit when 1,000 subscribers or a warm intro exists | T31: 2026-12-01 | U31: CEO | V31: not assessed
A32: S096 | B32: IKEA Portugal | C32: Home furnishing | D32: LU, FR, CH, BR | E32: C | F32: L | H32: Large or generic; no proof of spend on our audience | K32: Owner or marketing lead | L32: LinkedIn (named role); general partnerships email as backup | M32: Silver | N32: =INDEX(Settings!$B$4:$B$15,MATCH(M32,Settings!$A$4:$A$15,0)) | O32: =IF(E32="A",IF(I32>=2022,Settings!$B$18,Settings!$B$19),IF(E32="B",Settings!$B$20,Settings!$B$21))+IF(F32="S",Settings!$B$22,0) | P32: =N32*O32 | Q32: =P32*INDEX(Settings!$B$25:$B$27,MATCH(F32,Settings!$A$25:$A$27,0)) | R32: Parked | S32: Revisit when 1,000 subscribers or a warm intro exists | T32: 2026-12-01 | U32: CEO | V32: not assessed
A33: S097 | B33: ING Luxembourg | C33: Bank (Luxembourg) | D33: LU | E33: C | F33: L | H33: Large or generic; no proof of spend on our audience | K33: Marketing lead, non-resident / emigrant segment | L33: LinkedIn (named role); general partnerships email as backup | M33: Gold | N33: =INDEX(Settings!$B$4:$B$15,MATCH(M33,Settings!$A$4:$A$15,0)) | O33: =IF(E33="A",IF(I33>=2022,Settings!$B$18,Settings!$B$19),IF(E33="B",Settings!$B$20,Settings!$B$21))+IF(F33="S",Settings!$B$22,0) | P33: =N33*O33 | Q33: =P33*INDEX(Settings!$B$25:$B$27,MATCH(F33,Settings!$A$25:$A$27,0)) | R33: Parked | S33: Revisit when 1,000 subscribers or a warm intro exists | T33: 2026-12-01 | U33: CEO | V33: not assessed
A34: S143 | B34: Innovarisk | C34: Insurance | D34: LU, FR, CH, BR, US, IL | E34: C | F34: L | G34: https://www.doutorfinancas.pt/seguro-vida-geral/ | H34: Insurer listed as a partner by Doutor Finanças' insurance intermediary (Doutor Finanças Protege) (prompt 13); no proof of spend on our audience | I34: 2026 | J34: Fetched | K34: Marketing lead, intermediary / partnerships | L34: LinkedIn (named role); general partnerships email as backup | M34: Silver | N34: =INDEX(Settings!$B$4:$B$15,MATCH(M34,Settings!$A$4:$A$15,0)) | O34: =IF(E34="A",IF(I34>=2022,Settings!$B$18,Settings!$B$19),IF(E34="B",Settings!$B$20,Settings!$B$21))+IF(F34="S",Settings!$B$22,0) | P34: =N34*O34 | Q34: =P34*INDEX(Settings!$B$25:$B$27,MATCH(F34,Settings!$A$25:$A$27,0)) | R34: Parked | S34: Revisit when 1,000 subscribers or a warm intro exists | T34: 2026-12-01 | U34: CEO | V34: not assessed
A35: S098 | B35: Internorte | C35: Coach travel | D35: LU, FR, CH, BR | E35: C | F35: L | H35: Large or generic; no proof of spend on our audience | K35: Owner or marketing lead | L35: LinkedIn (named role); general partnerships email as backup | M35: Silver | N35: =INDEX(Settings!$B$4:$B$15,MATCH(M35,Settings!$A$4:$A$15,0)) | O35: =IF(E35="A",IF(I35>=2022,Settings!$B$18,Settings!$B$19),IF(E35="B",Settings!$B$20,Settings!$B$21))+IF(F35="S",Settings!$B$22,0) | P35: =N35*O35 | Q35: =P35*INDEX(Settings!$B$25:$B$27,MATCH(F35,Settings!$A$25:$A$27,0)) | R35: Parked | S35: Revisit when 1,000 subscribers or a warm intro exists | T35: 2026-12-01 | U35: CEO | V35: not assessed
A36: S099 | B36: JLL Portugal | C36: Real estate services | D36: LU, FR, CH, BR | E36: C | F36: L | H36: Large or generic; no proof of spend on our audience | K36: Owner or marketing lead | L36: LinkedIn (named role); general partnerships email as backup | M36: Silver | N36: =INDEX(Settings!$B$4:$B$15,MATCH(M36,Settings!$A$4:$A$15,0)) | O36: =IF(E36="A",IF(I36>=2022,Settings!$B$18,Settings!$B$19),IF(E36="B",Settings!$B$20,Settings!$B$21))+IF(F36="S",Settings!$B$22,0) | P36: =N36*O36 | Q36: =P36*INDEX(Settings!$B$25:$B$27,MATCH(F36,Settings!$A$25:$A$27,0)) | R36: Parked | S36: Revisit when 1,000 subscribers or a warm intro exists | T36: 2026-12-01 | U36: CEO | V36: not assessed
A37: S100 | B37: JPS Group | C37: Developer | D37: LU, FR, CH, BR | E37: C | F37: L | H37: Large or generic; no proof of spend on our audience | K37: Sales or marketing director | L37: LinkedIn (named role); general partnerships email as backup | M37: Silver | N37: =INDEX(Settings!$B$4:$B$15,MATCH(M37,Settings!$A$4:$A$15,0)) | O37: =IF(E37="A",IF(I37>=2022,Settings!$B$18,Settings!$B$19),IF(E37="B",Settings!$B$20,Settings!$B$21))+IF(F37="S",Settings!$B$22,0) | P37: =N37*O37 | Q37: =P37*INDEX(Settings!$B$25:$B$27,MATCH(F37,Settings!$A$25:$A$27,0)) | R37: Parked | S37: Revisit when 1,000 subscribers or a warm intro exists | T37: 2026-12-01 | U37: CEO | V37: not assessed
A38: S101 | B38: Kronos Homes | C38: Developer | D38: LU, FR, CH, BR | E38: C | F38: L | H38: Large or generic; no proof of spend on our audience | K38: Sales or marketing director | L38: LinkedIn (named role); general partnerships email as backup | M38: Silver | N38: =INDEX(Settings!$B$4:$B$15,MATCH(M38,Settings!$A$4:$A$15,0)) | O38: =IF(E38="A",IF(I38>=2022,Settings!$B$18,Settings!$B$19),IF(E38="B",Settings!$B$20,Settings!$B$21))+IF(F38="S",Settings!$B$22,0) | P38: =N38*O38 | Q38: =P38*INDEX(Settings!$B$25:$B$27,MATCH(F38,Settings!$A$25:$A$27,0)) | R38: Parked | S38: Revisit when 1,000 subscribers or a warm intro exists | T38: 2026-12-01 | U38: CEO | V38: not assessed
A39: S102 | B39: Lalux | C39: Insurance (Luxembourg) | D39: LU | E39: C | F39: L | H39: Large or generic; no proof of spend on our audience | K39: Marketing lead, retail | L39: LinkedIn (named role); general partnerships email as backup | M39: Silver | N39: =INDEX(Settings!$B$4:$B$15,MATCH(M39,Settings!$A$4:$A$15,0)) | O39: =IF(E39="A",IF(I39>=2022,Settings!$B$18,Settings!$B$19),IF(E39="B",Settings!$B$20,Settings!$B$21))+IF(F39="S",Settings!$B$22,0) | P39: =N39*O39 | Q39: =P39*INDEX(Settings!$B$25:$B$27,MATCH(F39,Settings!$A$25:$A$27,0)) | R39: Parked | S39: Revisit when 1,000 subscribers or a warm intro exists | T39: 2026-12-01 | U39: CEO | V39: not assessed
A40: S103 | B40: Leroy Merlin Portugal | C40: DIY / renovation | D40: LU, FR, CH, BR | E40: C | F40: L | H40: Large or generic; no proof of spend on our audience | K40: Owner or marketing lead | L40: LinkedIn (named role); general partnerships email as backup | M40: Silver | N40: =INDEX(Settings!$B$4:$B$15,MATCH(M40,Settings!$A$4:$A$15,0)) | O40: =IF(E40="A",IF(I40>=2022,Settings!$B$18,Settings!$B$19),IF(E40="B",Settings!$B$20,Settings!$B$21))+IF(F40="S",Settings!$B$22,0) | P40: =N40*O40 | Q40: =P40*INDEX(Settings!$B$25:$B$27,MATCH(F40,Settings!$A$25:$A$27,0)) | R40: Parked | S40: Revisit when 1,000 subscribers or a warm intro exists | T40: 2026-12-01 | U40: CEO | V40: not assessed
A41: S104 | B41: Lexidy | C41: Law firm | D41: LU, FR, CH, BR | E41: C | F41: L | H41: Large or generic; no proof of spend on our audience | K41: Managing partner or business development | L41: LinkedIn (named role); general partnerships email as backup | M41: Silver | N41: =INDEX(Settings!$B$4:$B$15,MATCH(M41,Settings!$A$4:$A$15,0)) | O41: =IF(E41="A",IF(I41>=2022,Settings!$B$18,Settings!$B$19),IF(E41="B",Settings!$B$20,Settings!$B$21))+IF(F41="S",Settings!$B$22,0) | P41: =N41*O41 | Q41: =P41*INDEX(Settings!$B$25:$B$27,MATCH(F41,Settings!$A$25:$A$27,0)) | R41: Parked | S41: Revisit when 1,000 subscribers or a warm intro exists | T41: 2026-12-01 | U41: CEO | V41: not assessed
A42: S105 | B42: MEO | C42: Telecom | D42: LU, FR, CH, BR | E42: C | F42: L | H42: Large or generic; no proof of spend on our audience | K42: Owner or marketing lead | L42: LinkedIn (named role); general partnerships email as backup | M42: Silver | N42: =INDEX(Settings!$B$4:$B$15,MATCH(M42,Settings!$A$4:$A$15,0)) | O42: =IF(E42="A",IF(I42>=2022,Settings!$B$18,Settings!$B$19),IF(E42="B",Settings!$B$20,Settings!$B$21))+IF(F42="S",Settings!$B$22,0) | P42: =N42*O42 | Q42: =P42*INDEX(Settings!$B$25:$B$27,MATCH(F42,Settings!$A$25:$A$27,0)) | R42: Parked | S42: Revisit when 1,000 subscribers or a warm intro exists | T42: 2026-12-01 | U42: CEO | V42: not assessed
A43: S149 | B43: MGEN | C43: Insurance | D43: LU, FR, CH, BR, US, IL | E43: C | F43: L | G43: https://www.doutorfinancas.pt/seguro-vida-geral/ | H43: Insurer listed as a partner by Doutor Finanças' insurance intermediary (Doutor Finanças Protege) (prompt 13); no proof of spend on our audience | I43: 2026 | J43: Fetched | K43: Marketing lead, intermediary / partnerships | L43: LinkedIn (named role); general partnerships email as backup | M43: Silver | N43: =INDEX(Settings!$B$4:$B$15,MATCH(M43,Settings!$A$4:$A$15,0)) | O43: =IF(E43="A",IF(I43>=2022,Settings!$B$18,Settings!$B$19),IF(E43="B",Settings!$B$20,Settings!$B$21))+IF(F43="S",Settings!$B$22,0) | P43: =N43*O43 | Q43: =P43*INDEX(Settings!$B$25:$B$27,MATCH(F43,Settings!$A$25:$A$27,0)) | R43: Parked | S43: Revisit when 1,000 subscribers or a warm intro exists | T43: 2026-12-01 | U43: CEO | V43: not assessed
A44: S134 | B44: Mapfre | C44: Insurance | D44: LU, FR, CH, BR, US, IL | E44: C | F44: L | G44: https://www.doutorfinancas.pt/seguro-vida-geral/ | H44: Insurer listed as a partner by Doutor Finanças' insurance intermediary (Doutor Finanças Protege) (prompt 13); no proof of spend on our audience | I44: 2026 | J44: Fetched | K44: Marketing lead, intermediary / partnerships | L44: LinkedIn (named role); general partnerships email as backup | M44: Silver | N44: =INDEX(Settings!$B$4:$B$15,MATCH(M44,Settings!$A$4:$A$15,0)) | O44: =IF(E44="A",IF(I44>=2022,Settings!$B$18,Settings!$B$19),IF(E44="B",Settings!$B$20,Settings!$B$21))+IF(F44="S",Settings!$B$22,0) | P44: =N44*O44 | Q44: =P44*INDEX(Settings!$B$25:$B$27,MATCH(F44,Settings!$A$25:$A$27,0)) | R44: Parked | S44: Revisit when 1,000 subscribers or a warm intro exists | T44: 2026-12-01 | U44: CEO | V44: not assessed
A45: S106 | B45: Martins Castro | C45: Law firm | D45: LU, FR, CH, BR | E45: C | F45: L | H45: Large or generic; no proof of spend on our audience | K45: Managing partner or business development | L45: LinkedIn (named role); general partnerships email as backup | M45: Silver | N45: =INDEX(Settings!$B$4:$B$15,MATCH(M45,Settings!$A$4:$A$15,0)) | O45: =IF(E45="A",IF(I45>=2022,Settings!$B$18,Settings!$B$19),IF(E45="B",Settings!$B$20,Settings!$B$21))+IF(F45="S",Settings!$B$22,0) | P45: =N45*O45 | Q45: =P45*INDEX(Settings!$B$25:$B$27,MATCH(F45,Settings!$A$25:$A$27,0)) | R45: Parked | S45: Revisit when 1,000 subscribers or a warm intro exists | T45: 2026-12-01 | U45: CEO | V45: not assessed
A46: S135 | B46: MetLife | C46: Insurance | D46: LU, FR, CH, BR, US, IL | E46: C | F46: L | G46: https://www.doutorfinancas.pt/seguro-vida-geral/ | H46: Insurer listed as a partner by Doutor Finanças' insurance intermediary (Doutor Finanças Protege) (prompt 13); no proof of spend on our audience | I46: 2026 | J46: Fetched | K46: Marketing lead, intermediary / partnerships | L46: LinkedIn (named role); general partnerships email as backup | M46: Silver | N46: =INDEX(Settings!$B$4:$B$15,MATCH(M46,Settings!$A$4:$A$15,0)) | O46: =IF(E46="A",IF(I46>=2022,Settings!$B$18,Settings!$B$19),IF(E46="B",Settings!$B$20,Settings!$B$21))+IF(F46="S",Settings!$B$22,0) | P46: =N46*O46 | Q46: =P46*INDEX(Settings!$B$25:$B$27,MATCH(F46,Settings!$A$25:$A$27,0)) | R46: Parked | S46: Revisit when 1,000 subscribers or a warm intro exists | T46: 2026-12-01 | U46: CEO | V46: not assessed
A47: S155 | B47: Mondego Capital Partners | C47: Developer / investor | D47: IL, US | E47: C | F47: S | G47: https://www.essential-business.pt/?p=11819 | H47: Porto-based; 45 M€ in luxury residential buildings in Lisbon (Chiado, Baixa, Marquês de Pombal), Jan 2021. Israeli link rests on a GRI Institute profile only; target buyers not stated | I47: 2021 | J47: Fetched | K47: Sales or marketing director | L47: Phone or email from company website, then LinkedIn | M47: Campaign | N47: =INDEX(Settings!$B$4:$B$15,MATCH(M47,Settings!$A$4:$A$15,0)) | O47: =IF(E47="A",IF(I47>=2022,Settings!$B$18,Settings!$B$19),IF(E47="B",Settings!$B$20,Settings!$B$21))+IF(F47="S",Settings!$B$22,0) | P47: =N47*O47 | Q47: =P47*INDEX(Settings!$B$25:$B$27,MATCH(F47,Settings!$A$25:$A$27,0)) | R47: Parked | S47: Revisit when 1,000 subscribers or a warm intro exists | T47: 2026-12-01 | U47: CEO | V47: Israel (to confirm)
A48: S107 | B48: Moneycorp | C48: FX | D48: LU, FR, CH, BR | E48: C | F48: L | H48: Large or generic; no proof of spend on our audience | K48: Partnerships / affiliates manager | L48: LinkedIn (named role); general partnerships email as backup | M48: Silver | N48: =INDEX(Settings!$B$4:$B$15,MATCH(M48,Settings!$A$4:$A$15,0)) | O48: =IF(E48="A",IF(I48>=2022,Settings!$B$18,Settings!$B$19),IF(E48="B",Settings!$B$20,Settings!$B$21))+IF(F48="S",Settings!$B$22,0) | P48: =N48*O48 | Q48: =P48*INDEX(Settings!$B$25:$B$27,MATCH(F48,Settings!$A$25:$A$27,0)) | R48: Parked | S48: Revisit when 1,000 subscribers or a warm intro exists | T48: 2026-12-01 | U48: CEO | V48: not assessed
A49: S108 | B49: NOS | C49: Telecom | D49: LU, FR, CH, BR | E49: C | F49: L | H49: Large or generic; no proof of spend on our audience | K49: Owner or marketing lead | L49: LinkedIn (named role); general partnerships email as backup | M49: Silver | N49: =INDEX(Settings!$B$4:$B$15,MATCH(M49,Settings!$A$4:$A$15,0)) | O49: =IF(E49="A",IF(I49>=2022,Settings!$B$18,Settings!$B$19),IF(E49="B",Settings!$B$20,Settings!$B$21))+IF(F49="S",Settings!$B$22,0) | P49: =N49*O49 | Q49: =P49*INDEX(Settings!$B$25:$B$27,MATCH(F49,Settings!$A$25:$A$27,0)) | R49: Parked | S49: Revisit when 1,000 subscribers or a warm intro exists | T49: 2026-12-01 | U49: CEO | V49: not assessed
A50: S109 | B50: Nomad | C50: Fintech (Brazil) | D50: BR | E50: C | F50: L | H50: Large or generic; no proof of spend on our audience | K50: Partnerships / affiliates manager | L50: LinkedIn (named role); general partnerships email as backup | M50: Silver | N50: =INDEX(Settings!$B$4:$B$15,MATCH(M50,Settings!$A$4:$A$15,0)) | O50: =IF(E50="A",IF(I50>=2022,Settings!$B$18,Settings!$B$19),IF(E50="B",Settings!$B$20,Settings!$B$21))+IF(F50="S",Settings!$B$22,0) | P50: =N50*O50 | Q50: =P50*INDEX(Settings!$B$25:$B$27,MATCH(F50,Settings!$A$25:$A$27,0)) | R50: Parked | S50: Revisit when 1,000 subscribers or a warm intro exists | T50: 2026-12-01 | U50: CEO | V50: not assessed
A51: S110 | B51: Pestana Residences | C51: Developer / hospitality | D51: LU, FR, CH, BR | E51: C | F51: L | H51: Large or generic; no proof of spend on our audience | K51: Sales or marketing director | L51: LinkedIn (named role); general partnerships email as backup | M51: Silver | N51: =INDEX(Settings!$B$4:$B$15,MATCH(M51,Settings!$A$4:$A$15,0)) | O51: =IF(E51="A",IF(I51>=2022,Settings!$B$18,Settings!$B$19),IF(E51="B",Settings!$B$20,Settings!$B$21))+IF(F51="S",Settings!$B$22,0) | P51: =N51*O51 | Q51: =P51*INDEX(Settings!$B$25:$B$27,MATCH(F51,Settings!$A$25:$A$27,0)) | R51: Parked | S51: Revisit when 1,000 subscribers or a warm intro exists | T51: 2026-12-01 | U51: CEO | V51: not assessed
A52: S111 | B52: PostFinance | C52: Bank (Switzerland) | D52: CH | E52: C | F52: L | H52: Large or generic; no proof of spend on our audience | K52: Marketing lead, non-resident / emigrant segment | L52: LinkedIn (named role); general partnerships email as backup | M52: Gold | N52: =INDEX(Settings!$B$4:$B$15,MATCH(M52,Settings!$A$4:$A$15,0)) | O52: =IF(E52="A",IF(I52>=2022,Settings!$B$18,Settings!$B$19),IF(E52="B",Settings!$B$20,Settings!$B$21))+IF(F52="S",Settings!$B$22,0) | P52: =N52*O52 | Q52: =P52*INDEX(Settings!$B$25:$B$27,MATCH(F52,Settings!$A$25:$A$27,0)) | R52: Parked | S52: Revisit when 1,000 subscribers or a warm intro exists | T52: 2026-12-01 | U52: CEO | V52: not assessed
A53: S136 | B53: Prévoir | C53: Insurance | D53: LU, FR, CH, BR, US, IL | E53: C | F53: L | G53: https://www.doutorfinancas.pt/seguro-vida-geral/ | H53: Insurer listed as a partner by Doutor Finanças' insurance intermediary (Doutor Finanças Protege) (prompt 13); no proof of spend on our audience | I53: 2026 | J53: Fetched | K53: Marketing lead, intermediary / partnerships | L53: LinkedIn (named role); general partnerships email as backup | M53: Silver | N53: =INDEX(Settings!$B$4:$B$15,MATCH(M53,Settings!$A$4:$A$15,0)) | O53: =IF(E53="A",IF(I53>=2022,Settings!$B$18,Settings!$B$19),IF(E53="B",Settings!$B$20,Settings!$B$21))+IF(F53="S",Settings!$B$22,0) | P53: =N53*O53 | Q53: =P53*INDEX(Settings!$B$25:$B$27,MATCH(F53,Settings!$A$25:$A$27,0)) | R53: Parked | S53: Revisit when 1,000 subscribers or a warm intro exists | T53: 2026-12-01 | U53: CEO | V53: not assessed
A54: S112 | B54: RFF Lawyers | C54: Law / tax | D54: LU, FR, CH, BR | E54: C | F54: L | H54: Large or generic; no proof of spend on our audience | K54: Managing partner or business development | L54: LinkedIn (named role); general partnerships email as backup | M54: Silver | N54: =INDEX(Settings!$B$4:$B$15,MATCH(M54,Settings!$A$4:$A$15,0)) | O54: =IF(E54="A",IF(I54>=2022,Settings!$B$18,Settings!$B$19),IF(E54="B",Settings!$B$20,Settings!$B$21))+IF(F54="S",Settings!$B$22,0) | P54: =N54*O54 | Q54: =P54*INDEX(Settings!$B$25:$B$27,MATCH(F54,Settings!$A$25:$A$27,0)) | R54: Parked | S54: Revisit when 1,000 subscribers or a warm intro exists | T54: 2026-12-01 | U54: CEO | V54: not assessed
A55: S113 | B55: Raiffeisen Suisse | C55: Bank (Switzerland) | D55: CH | E55: C | F55: L | H55: Large or generic; no proof of spend on our audience | K55: Marketing lead, non-resident / emigrant segment | L55: LinkedIn (named role); general partnerships email as backup | M55: Gold | N55: =INDEX(Settings!$B$4:$B$15,MATCH(M55,Settings!$A$4:$A$15,0)) | O55: =IF(E55="A",IF(I55>=2022,Settings!$B$18,Settings!$B$19),IF(E55="B",Settings!$B$20,Settings!$B$21))+IF(F55="S",Settings!$B$22,0) | P55: =N55*O55 | Q55: =P55*INDEX(Settings!$B$25:$B$27,MATCH(F55,Settings!$A$25:$A$27,0)) | R55: Parked | S55: Revisit when 1,000 subscribers or a warm intro exists | T55: 2026-12-01 | U55: CEO | V55: not assessed
A56: S137 | B56: Real Vida Seguros | C56: Insurance | D56: LU, FR, CH, BR, US, IL | E56: C | F56: L | G56: https://www.doutorfinancas.pt/seguro-vida-geral/ | H56: Insurer listed as a partner by Doutor Finanças' insurance intermediary (Doutor Finanças Protege) (prompt 13); no proof of spend on our audience | I56: 2026 | J56: Fetched | K56: Marketing lead, intermediary / partnerships | L56: LinkedIn (named role); general partnerships email as backup | M56: Silver | N56: =INDEX(Settings!$B$4:$B$15,MATCH(M56,Settings!$A$4:$A$15,0)) | O56: =IF(E56="A",IF(I56>=2022,Settings!$B$18,Settings!$B$19),IF(E56="B",Settings!$B$20,Settings!$B$21))+IF(F56="S",Settings!$B$22,0) | P56: =N56*O56 | Q56: =P56*INDEX(Settings!$B$25:$B$27,MATCH(F56,Settings!$A$25:$A$27,0)) | R56: Parked | S56: Revisit when 1,000 subscribers or a warm intro exists | T56: 2026-12-01 | U56: CEO | V56: not assessed
A57: S114 | B57: Revolut | C57: Fintech | D57: LU, FR, CH, BR | E57: C | F57: L | H57: Large or generic; no proof of spend on our audience | K57: Partnerships / affiliates manager | L57: LinkedIn (named role); general partnerships email as backup | M57: Silver | N57: =INDEX(Settings!$B$4:$B$15,MATCH(M57,Settings!$A$4:$A$15,0)) | O57: =IF(E57="A",IF(I57>=2022,Settings!$B$18,Settings!$B$19),IF(E57="B",Settings!$B$20,Settings!$B$21))+IF(F57="S",Settings!$B$22,0) | P57: =N57*O57 | Q57: =P57*INDEX(Settings!$B$25:$B$27,MATCH(F57,Settings!$A$25:$A$27,0)) | R57: Parked | S57: Revisit when 1,000 subscribers or a warm intro exists | T57: 2026-12-01 | U57: CEO | V57: not assessed
A58: S115 | B58: SRS Legal | C58: Law firm | D58: LU, FR, CH, BR | E58: C | F58: L | H58: Large or generic; no proof of spend on our audience | K58: Managing partner or business development | L58: LinkedIn (named role); general partnerships email as backup | M58: Silver | N58: =INDEX(Settings!$B$4:$B$15,MATCH(M58,Settings!$A$4:$A$15,0)) | O58: =IF(E58="A",IF(I58>=2022,Settings!$B$18,Settings!$B$19),IF(E58="B",Settings!$B$20,Settings!$B$21))+IF(F58="S",Settings!$B$22,0) | P58: =N58*O58 | Q58: =P58*INDEX(Settings!$B$25:$B$27,MATCH(F58,Settings!$A$25:$A$27,0)) | R58: Parked | S58: Revisit when 1,000 subscribers or a warm intro exists | T58: 2026-12-01 | U58: CEO | V58: not assessed
A59: S148 | B59: Saúde Prime | C59: Insurance | D59: LU, FR, CH, BR, US, IL | E59: C | F59: L | G59: https://www.doutorfinancas.pt/seguro-vida-geral/ | H59: Insurer listed as a partner by Doutor Finanças' insurance intermediary (Doutor Finanças Protege) (prompt 13); no proof of spend on our audience | I59: 2026 | J59: Fetched | K59: Marketing lead, intermediary / partnerships | L59: LinkedIn (named role); general partnerships email as backup | M59: Silver | N59: =INDEX(Settings!$B$4:$B$15,MATCH(M59,Settings!$A$4:$A$15,0)) | O59: =IF(E59="A",IF(I59>=2022,Settings!$B$18,Settings!$B$19),IF(E59="B",Settings!$B$20,Settings!$B$21))+IF(F59="S",Settings!$B$22,0) | P59: =N59*O59 | Q59: =P59*INDEX(Settings!$B$25:$B$27,MATCH(F59,Settings!$A$25:$A$27,0)) | R59: Parked | S59: Revisit when 1,000 subscribers or a warm intro exists | T59: 2026-12-01 | U59: CEO | V59: not assessed
A60: S116 | B60: Spuerkeess | C60: Bank (Luxembourg) | D60: LU | E60: C | F60: L | H60: Large or generic; no proof of spend on our audience | K60: Marketing lead, non-resident / emigrant segment | L60: LinkedIn (named role); general partnerships email as backup | M60: Gold | N60: =INDEX(Settings!$B$4:$B$15,MATCH(M60,Settings!$A$4:$A$15,0)) | O60: =IF(E60="A",IF(I60>=2022,Settings!$B$18,Settings!$B$19),IF(E60="B",Settings!$B$20,Settings!$B$21))+IF(F60="S",Settings!$B$22,0) | P60: =N60*O60 | Q60: =P60*INDEX(Settings!$B$25:$B$27,MATCH(F60,Settings!$A$25:$A$27,0)) | R60: Parked | S60: Revisit when 1,000 subscribers or a warm intro exists | T60: 2026-12-01 | U60: CEO | V60: not assessed
A61: S117 | B61: Swiss Life | C61: Pensions (Switzerland) | D61: CH | E61: C | F61: L | H61: Large or generic; no proof of spend on our audience | K61: Owner or marketing lead | L61: LinkedIn (named role); general partnerships email as backup | M61: Silver | N61: =INDEX(Settings!$B$4:$B$15,MATCH(M61,Settings!$A$4:$A$15,0)) | O61: =IF(E61="A",IF(I61>=2022,Settings!$B$18,Settings!$B$19),IF(E61="B",Settings!$B$20,Settings!$B$21))+IF(F61="S",Settings!$B$22,0) | P61: =N61*O61 | Q61: =P61*INDEX(Settings!$B$25:$B$27,MATCH(F61,Settings!$A$25:$A$27,0)) | R61: Parked | S61: Revisit when 1,000 subscribers or a warm intro exists | T61: 2026-12-01 | U61: CEO | V61: not assessed
A62: S118 | B62: TAP Air Portugal | C62: Airline | D62: LU, FR, CH, BR | E62: C | F62: L | H62: Large or generic; no proof of spend on our audience | K62: Owner or marketing lead | L62: LinkedIn (named role); general partnerships email as backup | M62: Gold | N62: =INDEX(Settings!$B$4:$B$15,MATCH(M62,Settings!$A$4:$A$15,0)) | O62: =IF(E62="A",IF(I62>=2022,Settings!$B$18,Settings!$B$19),IF(E62="B",Settings!$B$20,Settings!$B$21))+IF(F62="S",Settings!$B$22,0) | P62: =N62*O62 | Q62: =P62*INDEX(Settings!$B$25:$B$27,MATCH(F62,Settings!$A$25:$A$27,0)) | R62: Parked | S62: Revisit when 1,000 subscribers or a warm intro exists | T62: 2026-12-01 | U62: CEO | V62: not assessed
A63: S119 | B63: Taxx | C63: Tax returns (Luxembourg) | D63: LU | E63: C | F63: L | H63: Large or generic; no proof of spend on our audience | K63: Owner or marketing lead | L63: LinkedIn (named role); general partnerships email as backup | M63: Silver | N63: =INDEX(Settings!$B$4:$B$15,MATCH(M63,Settings!$A$4:$A$15,0)) | O63: =IF(E63="A",IF(I63>=2022,Settings!$B$18,Settings!$B$19),IF(E63="B",Settings!$B$20,Settings!$B$21))+IF(F63="S",Settings!$B$22,0) | P63: =N63*O63 | Q63: =P63*INDEX(Settings!$B$25:$B$27,MATCH(F63,Settings!$A$25:$A$27,0)) | R63: Parked | S63: Revisit when 1,000 subscribers or a warm intro exists | T63: 2026-12-01 | U63: CEO | V63: not assessed
A64: S120 | B64: Telles | C64: Law firm | D64: LU, FR, CH, BR | E64: C | F64: L | H64: Large or generic; no proof of spend on our audience | K64: Managing partner or business development | L64: LinkedIn (named role); general partnerships email as backup | M64: Silver | N64: =INDEX(Settings!$B$4:$B$15,MATCH(M64,Settings!$A$4:$A$15,0)) | O64: =IF(E64="A",IF(I64>=2022,Settings!$B$18,Settings!$B$19),IF(E64="B",Settings!$B$20,Settings!$B$21))+IF(F64="S",Settings!$B$22,0) | P64: =N64*O64 | Q64: =P64*INDEX(Settings!$B$25:$B$27,MATCH(F64,Settings!$A$25:$A$27,0)) | R64: Parked | S64: Revisit when 1,000 subscribers or a warm intro exists | T64: 2026-12-01 | U64: CEO | V64: not assessed
A65: S138 | B65: Una Seguros | C65: Insurance | D65: LU, FR, CH, BR, US, IL | E65: C | F65: L | G65: https://www.doutorfinancas.pt/seguro-vida-geral/ | H65: Insurer listed as a partner by Doutor Finanças' insurance intermediary (Doutor Finanças Protege) (prompt 13); no proof of spend on our audience | I65: 2026 | J65: Fetched | K65: Marketing lead, intermediary / partnerships | L65: LinkedIn (named role); general partnerships email as backup | M65: Silver | N65: =INDEX(Settings!$B$4:$B$15,MATCH(M65,Settings!$A$4:$A$15,0)) | O65: =IF(E65="A",IF(I65>=2022,Settings!$B$18,Settings!$B$19),IF(E65="B",Settings!$B$20,Settings!$B$21))+IF(F65="S",Settings!$B$22,0) | P65: =N65*O65 | Q65: =P65*INDEX(Settings!$B$25:$B$27,MATCH(F65,Settings!$A$25:$A$27,0)) | R65: Parked | S65: Revisit when 1,000 subscribers or a warm intro exists | T65: 2026-12-01 | U65: CEO | V65: not assessed
A66: S122 | B66: VZ VermögensZentrum | C66: Pension advice (Switzerland) | D66: CH | E66: C | F66: L | H66: Large or generic; no proof of spend on our audience | K66: Owner or marketing lead | L66: LinkedIn (named role); general partnerships email as backup | M66: Silver | N66: =INDEX(Settings!$B$4:$B$15,MATCH(M66,Settings!$A$4:$A$15,0)) | O66: =IF(E66="A",IF(I66>=2022,Settings!$B$18,Settings!$B$19),IF(E66="B",Settings!$B$20,Settings!$B$21))+IF(F66="S",Settings!$B$22,0) | P66: =N66*O66 | Q66: =P66*INDEX(Settings!$B$25:$B$27,MATCH(F66,Settings!$A$25:$A$27,0)) | R66: Parked | S66: Revisit when 1,000 subscribers or a warm intro exists | T66: 2026-12-01 | U66: CEO | V66: not assessed
A67: S139 | B67: Victoria Seguros | C67: Insurance | D67: LU, FR, CH, BR, US, IL | E67: C | F67: L | G67: https://www.doutorfinancas.pt/seguro-vida-geral/ | H67: Insurer listed as a partner by Doutor Finanças' insurance intermediary (Doutor Finanças Protege) (prompt 13); no proof of spend on our audience | I67: 2026 | J67: Fetched | K67: Marketing lead, intermediary / partnerships | L67: LinkedIn (named role); general partnerships email as backup | M67: Silver | N67: =INDEX(Settings!$B$4:$B$15,MATCH(M67,Settings!$A$4:$A$15,0)) | O67: =IF(E67="A",IF(I67>=2022,Settings!$B$18,Settings!$B$19),IF(E67="B",Settings!$B$20,Settings!$B$21))+IF(F67="S",Settings!$B$22,0) | P67: =N67*O67 | Q67: =P67*INDEX(Settings!$B$25:$B$27,MATCH(F67,Settings!$A$25:$A$27,0)) | R67: Parked | S67: Revisit when 1,000 subscribers or a warm intro exists | T67: 2026-12-01 | U67: CEO | V67: not assessed
A68: S124 | B68: XP Investimentos | C68: Investments (Brazil) | D68: BR | E68: C | F68: L | H68: Large or generic; no proof of spend on our audience | K68: Owner or marketing lead | L68: LinkedIn (named role); general partnerships email as backup | M68: Silver | N68: =INDEX(Settings!$B$4:$B$15,MATCH(M68,Settings!$A$4:$A$15,0)) | O68: =IF(E68="A",IF(I68>=2022,Settings!$B$18,Settings!$B$19),IF(E68="B",Settings!$B$20,Settings!$B$21))+IF(F68="S",Settings!$B$22,0) | P68: =N68*O68 | Q68: =P68*INDEX(Settings!$B$25:$B$27,MATCH(F68,Settings!$A$25:$A$27,0)) | R68: Parked | S68: Revisit when 1,000 subscribers or a warm intro exists | T68: 2026-12-01 | U68: CEO | V68: not assessed
A69: S125 | B69: Zaask | C69: Services marketplace | D69: LU, FR, CH, BR | E69: C | F69: L | H69: Large or generic; no proof of spend on our audience | K69: Owner or marketing lead | L69: LinkedIn (named role); general partnerships email as backup | M69: Silver | N69: =INDEX(Settings!$B$4:$B$15,MATCH(M69,Settings!$A$4:$A$15,0)) | O69: =IF(E69="A",IF(I69>=2022,Settings!$B$18,Settings!$B$19),IF(E69="B",Settings!$B$20,Settings!$B$21))+IF(F69="S",Settings!$B$22,0) | P69: =N69*O69 | Q69: =P69*INDEX(Settings!$B$25:$B$27,MATCH(F69,Settings!$A$25:$A$27,0)) | R69: Parked | S69: Revisit when 1,000 subscribers or a warm intro exists | T69: 2026-12-01 | U69: CEO | V69: not assessed
A70: S140 | B70: Zurich Portugal | C70: Insurance | D70: LU, FR, CH, BR, US, IL | E70: C | F70: L | G70: https://www.doutorfinancas.pt/seguro-vida-geral/ | H70: Insurer listed as a partner by Doutor Finanças' insurance intermediary (Doutor Finanças Protege) (prompt 13); no proof of spend on our audience | I70: 2026 | J70: Fetched | K70: Marketing lead, intermediary / partnerships | L70: LinkedIn (named role); general partnerships email as backup | M70: Silver | N70: =INDEX(Settings!$B$4:$B$15,MATCH(M70,Settings!$A$4:$A$15,0)) | O70: =IF(E70="A",IF(I70>=2022,Settings!$B$18,Settings!$B$19),IF(E70="B",Settings!$B$20,Settings!$B$21))+IF(F70="S",Settings!$B$22,0) | P70: =N70*O70 | Q70: =P70*INDEX(Settings!$B$25:$B$27,MATCH(F70,Settings!$A$25:$A$27,0)) | R70: Parked | S70: Revisit when 1,000 subscribers or a warm intro exists | T70: 2026-12-01 | U70: CEO | V70: not assessed

Sheet This week's 40
A1: # | B1: ID | C1: Company | D1: Editions | E1: Tier | F1: Offer | G1: Expected value (€) | H1: Priority score | I1: Who to reach | J1: Channel | K1: Send on | L1: Status
A2: 1 | B2: S001 | C2: =INDEX('Pipeline A-B'!$B$2:$B$132,MATCH($B2,'Pipeline A-B'!$A$2:$A$132,0)) | D2: =INDEX('Pipeline A-B'!$D$2:$D$132,MATCH($B2,'Pipeline A-B'!$A$2:$A$132,0)) | E2: =INDEX('Pipeline A-B'!$E$2:$E$132,MATCH($B2,'Pipeline A-B'!$A$2:$A$132,0)) | F2: =INDEX('Pipeline A-B'!$M$2:$M$132,MATCH($B2,'Pipeline A-B'!$A$2:$A$132,0)) | G2: =INDEX('Pipeline A-B'!$P$2:$P$132,MATCH($B2,'Pipeline A-B'!$A$2:$A$132,0)) | H2: =INDEX('Pipeline A-B'!$Q$2:$Q$132,MATCH($B2,'Pipeline A-B'!$A$2:$A$132,0)) | I2: =INDEX('Pipeline A-B'!$K$2:$K$132,MATCH($B2,'Pipeline A-B'!$A$2:$A$132,0)) | J2: =INDEX('Pipeline A-B'!$L$2:$L$132,MATCH($B2,'Pipeline A-B'!$A$2:$A$132,0)) | K2: =INDEX('Pipeline A-B'!$T$2:$T$132,MATCH($B2,'Pipeline A-B'!$A$2:$A$132,0)) | L2: =INDEX('Pipeline A-B'!$R$2:$R$132,MATCH($B2,'Pipeline A-B'!$A$2:$A$132,0))
A3: 2 | B3: S002 | C3: =INDEX('Pipeline A-B'!$B$2:$B$132,MATCH($B3,'Pipeline A-B'!$A$2:$A$132,0)) | D3: =INDEX('Pipeline A-B'!$D$2:$D$132,MATCH($B3,'Pipeline A-B'!$A$2:$A$132,0)) | E3: =INDEX('Pipeline A-B'!$E$2:$E$132,MATCH($B3,'Pipeline A-B'!$A$2:$A$132,0)) | F3: =INDEX('Pipeline A-B'!$M$2:$M$132,MATCH($B3,'Pipeline A-B'!$A$2:$A$132,0)) | G3: =INDEX('Pipeline A-B'!$P$2:$P$132,MATCH($B3,'Pipeline A-B'!$A$2:$A$132,0)) | H3: =INDEX('Pipeline A-B'!$Q$2:$Q$132,MATCH($B3,'Pipeline A-B'!$A$2:$A$132,0)) | I3: =INDEX('Pipeline A-B'!$K$2:$K$132,MATCH($B3,'Pipeline A-B'!$A$2:$A$132,0)) | J3: =INDEX('Pipeline A-B'!$L$2:$L$132,MATCH($B3,'Pipeline A-B'!$A$2:$A$132,0)) | K3: =INDEX('Pipeline A-B'!$T$2:$T$132,MATCH($B3,'Pipeline A-B'!$A$2:$A$132,0)) | L3: =INDEX('Pipeline A-B'!$R$2:$R$132,MATCH($B3,'Pipeline A-B'!$A$2:$A$132,0))
A4: 3 | B4: S003 | C4: =INDEX('Pipeline A-B'!$B$2:$B$132,MATCH($B4,'Pipeline A-B'!$A$2:$A$132,0)) | D4: =INDEX('Pipeline A-B'!$D$2:$D$132,MATCH($B4,'Pipeline A-B'!$A$2:$A$132,0)) | E4: =INDEX('Pipeline A-B'!$E$2:$E$132,MATCH($B4,'Pipeline A-B'!$A$2:$A$132,0)) | F4: =INDEX('Pipeline A-B'!$M$2:$M$132,MATCH($B4,'Pipeline A-B'!$A$2:$A$132,0)) | G4: =INDEX('Pipeline A-B'!$P$2:$P$132,MATCH($B4,'Pipeline A-B'!$A$2:$A$132,0)) | H4: =INDEX('Pipeline A-B'!$Q$2:$Q$132,MATCH($B4,'Pipeline A-B'!$A$2:$A$132,0)) | I4: =INDEX('Pipeline A-B'!$K$2:$K$132,MATCH($B4,'Pipeline A-B'!$A$2:$A$132,0)) | J4: =INDEX('Pipeline A-B'!$L$2:$L$132,MATCH($B4,'Pipeline A-B'!$A$2:$A$132,0)) | K4: =INDEX('Pipeline A-B'!$T$2:$T$132,MATCH($B4,'Pipeline A-B'!$A$2:$A$132,0)) | L4: =INDEX('Pipeline A-B'!$R$2:$R$132,MATCH($B4,'Pipeline A-B'!$A$2:$A$132,0))
A5: 4 | B5: S004 | C5: =INDEX('Pipeline A-B'!$B$2:$B$132,MATCH($B5,'Pipeline A-B'!$A$2:$A$132,0)) | D5: =INDEX('Pipeline A-B'!$D$2:$D$132,MATCH($B5,'Pipeline A-B'!$A$2:$A$132,0)) | E5: =INDEX('Pipeline A-B'!$E$2:$E$132,MATCH($B5,'Pipeline A-B'!$A$2:$A$132,0)) | F5: =INDEX('Pipeline A-B'!$M$2:$M$132,MATCH($B5,'Pipeline A-B'!$A$2:$A$132,0)) | G5: =INDEX('Pipeline A-B'!$P$2:$P$132,MATCH($B5,'Pipeline A-B'!$A$2:$A$132,0)) | H5: =INDEX('Pipeline A-B'!$Q$2:$Q$132,MATCH($B5,'Pipeline A-B'!$A$2:$A$132,0)) | I5: =INDEX('Pipeline A-B'!$K$2:$K$132,MATCH($B5,'Pipeline A-B'!$A$2:$A$132,0)) | J5: =INDEX('Pipeline A-B'!$L$2:$L$132,MATCH($B5,'Pipeline A-B'!$A$2:$A$132,0)) | K5: =INDEX('Pipeline A-B'!$T$2:$T$132,MATCH($B5,'Pipeline A-B'!$A$2:$A$132,0)) | L5: =INDEX('Pipeline A-B'!$R$2:$R$132,MATCH($B5,'Pipeline A-B'!$A$2:$A$132,0))
A6: 5 | B6: S005 | C6: =INDEX('Pipeline A-B'!$B$2:$B$132,MATCH($B6,'Pipeline A-B'!$A$2:$A$132,0)) | D6: =INDEX('Pipeline A-B'!$D$2:$D$132,MATCH($B6,'Pipeline A-B'!$A$2:$A$132,0)) | E6: =INDEX('Pipeline A-B'!$E$2:$E$132,MATCH($B6,'Pipeline A-B'!$A$2:$A$132,0)) | F6: =INDEX('Pipeline A-B'!$M$2:$M$132,MATCH($B6,'Pipeline A-B'!$A$2:$A$132,0)) | G6: =INDEX('Pipeline A-B'!$P$2:$P$132,MATCH($B6,'Pipeline A-B'!$A$2:$A$132,0)) | H6: =INDEX('Pipeline A-B'!$Q$2:$Q$132,MATCH($B6,'Pipeline A-B'!$A$2:$A$132,0)) | I6: =INDEX('Pipeline A-B'!$K$2:$K$132,MATCH($B6,'Pipeline A-B'!$A$2:$A$132,0)) | J6: =INDEX('Pipeline A-B'!$L$2:$L$132,MATCH($B6,'Pipeline A-B'!$A$2:$A$132,0)) | K6: =INDEX('Pipeline A-B'!$T$2:$T$132,MATCH($B6,'Pipeline A-B'!$A$2:$A$132,0)) | L6: =INDEX('Pipeline A-B'!$R$2:$R$132,MATCH($B6,'Pipeline A-B'!$A$2:$A$132,0))
A7: 6 | B7: S006 | C7: =INDEX('Pipeline A-B'!$B$2:$B$132,MATCH($B7,'Pipeline A-B'!$A$2:$A$132,0)) | D7: =INDEX('Pipeline A-B'!$D$2:$D$132,MATCH($B7,'Pipeline A-B'!$A$2:$A$132,0)) | E7: =INDEX('Pipeline A-B'!$E$2:$E$132,MATCH($B7,'Pipeline A-B'!$A$2:$A$132,0)) | F7: =INDEX('Pipeline A-B'!$M$2:$M$132,MATCH($B7,'Pipeline A-B'!$A$2:$A$132,0)) | G7: =INDEX('Pipeline A-B'!$P$2:$P$132,MATCH($B7,'Pipeline A-B'!$A$2:$A$132,0)) | H7: =INDEX('Pipeline A-B'!$Q$2:$Q$132,MATCH($B7,'Pipeline A-B'!$A$2:$A$132,0)) | I7: =INDEX('Pipeline A-B'!$K$2:$K$132,MATCH($B7,'Pipeline A-B'!$A$2:$A$132,0)) | J7: =INDEX('Pipeline A-B'!$L$2:$L$132,MATCH($B7,'Pipeline A-B'!$A$2:$A$132,0)) | K7: =INDEX('Pipeline A-B'!$T$2:$T$132,MATCH($B7,'Pipeline A-B'!$A$2:$A$132,0)) | L7: =INDEX('Pipeline A-B'!$R$2:$R$132,MATCH($B7,'Pipeline A-B'!$A$2:$A$132,0))
A8: 7 | B8: S007 | C8: =INDEX('Pipeline A-B'!$B$2:$B$132,MATCH($B8,'Pipeline A-B'!$A$2:$A$132,0)) | D8: =INDEX('Pipeline A-B'!$D$2:$D$132,MATCH($B8,'Pipeline A-B'!$A$2:$A$132,0)) | E8: =INDEX('Pipeline A-B'!$E$2:$E$132,MATCH($B8,'Pipeline A-B'!$A$2:$A$132,0)) | F8: =INDEX('Pipeline A-B'!$M$2:$M$132,MATCH($B8,'Pipeline A-B'!$A$2:$A$132,0)) | G8: =INDEX('Pipeline A-B'!$P$2:$P$132,MATCH($B8,'Pipeline A-B'!$A$2:$A$132,0)) | H8: =INDEX('Pipeline A-B'!$Q$2:$Q$132,MATCH($B8,'Pipeline A-B'!$A$2:$A$132,0)) | I8: =INDEX('Pipeline A-B'!$K$2:$K$132,MATCH($B8,'Pipeline A-B'!$A$2:$A$132,0)) | J8: =INDEX('Pipeline A-B'!$L$2:$L$132,MATCH($B8,'Pipeline A-B'!$A$2:$A$132,0)) | K8: =INDEX('Pipeline A-B'!$T$2:$T$132,MATCH($B8,'Pipeline A-B'!$A$2:$A$132,0)) | L8: =INDEX('Pipeline A-B'!$R$2:$R$132,MATCH($B8,'Pipeline A-B'!$A$2:$A$132,0))
A9: 8 | B9: S008 | C9: =INDEX('Pipeline A-B'!$B$2:$B$132,MATCH($B9,'Pipeline A-B'!$A$2:$A$132,0)) | D9: =INDEX('Pipeline A-B'!$D$2:$D$132,MATCH($B9,'Pipeline A-B'!$A$2:$A$132,0)) | E9: =INDEX('Pipeline A-B'!$E$2:$E$132,MATCH($B9,'Pipeline A-B'!$A$2:$A$132,0)) | F9: =INDEX('Pipeline A-B'!$M$2:$M$132,MATCH($B9,'Pipeline A-B'!$A$2:$A$132,0)) | G9: =INDEX('Pipeline A-B'!$P$2:$P$132,MATCH($B9,'Pipeline A-B'!$A$2:$A$132,0)) | H9: =INDEX('Pipeline A-B'!$Q$2:$Q$132,MATCH($B9,'Pipeline A-B'!$A$2:$A$132,0)) | I9: =INDEX('Pipeline A-B'!$K$2:$K$132,MATCH($B9,'Pipeline A-B'!$A$2:$A$132,0)) | J9: =INDEX('Pipeline A-B'!$L$2:$L$132,MATCH($B9,'Pipeline A-B'!$A$2:$A$132,0)) | K9: =INDEX('Pipeline A-B'!$T$2:$T$132,MATCH($B9,'Pipeline A-B'!$A$2:$A$132,0)) | L9: =INDEX('Pipeline A-B'!$R$2:$R$132,MATCH($B9,'Pipeline A-B'!$A$2:$A$132,0))
A10: 9 | B10: S009 | C10: =INDEX('Pipeline A-B'!$B$2:$B$132,MATCH($B10,'Pipeline A-B'!$A$2:$A$132,0)) | D10: =INDEX('Pipeline A-B'!$D$2:$D$132,MATCH($B10,'Pipeline A-B'!$A$2:$A$132,0)) | E10: =INDEX('Pipeline A-B'!$E$2:$E$132,MATCH($B10,'Pipeline A-B'!$A$2:$A$132,0)) | F10: =INDEX('Pipeline A-B'!$M$2:$M$132,MATCH($B10,'Pipeline A-B'!$A$2:$A$132,0)) | G10: =INDEX('Pipeline A-B'!$P$2:$P$132,MATCH($B10,'Pipeline A-B'!$A$2:$A$132,0)) | H10: =INDEX('Pipeline A-B'!$Q$2:$Q$132,MATCH($B10,'Pipeline A-B'!$A$2:$A$132,0)) | I10: =INDEX('Pipeline A-B'!$K$2:$K$132,MATCH($B10,'Pipeline A-B'!$A$2:$A$132,0)) | J10: =INDEX('Pipeline A-B'!$L$2:$L$132,MATCH($B10,'Pipeline A-B'!$A$2:$A$132,0)) | K10: =INDEX('Pipeline A-B'!$T$2:$T$132,MATCH($B10,'Pipeline A-B'!$A$2:$A$132,0)) | L10: =INDEX('Pipeline A-B'!$R$2:$R$132,MATCH($B10,'Pipeline A-B'!$A$2:$A$132,0))
A11: 10 | B11: S010 | C11: =INDEX('Pipeline A-B'!$B$2:$B$132,MATCH($B11,'Pipeline A-B'!$A$2:$A$132,0)) | D11: =INDEX('Pipeline A-B'!$D$2:$D$132,MATCH($B11,'Pipeline A-B'!$A$2:$A$132,0)) | E11: =INDEX('Pipeline A-B'!$E$2:$E$132,MATCH($B11,'Pipeline A-B'!$A$2:$A$132,0)) | F11: =INDEX('Pipeline A-B'!$M$2:$M$132,MATCH($B11,'Pipeline A-B'!$A$2:$A$132,0)) | G11: =INDEX('Pipeline A-B'!$P$2:$P$132,MATCH($B11,'Pipeline A-B'!$A$2:$A$132,0)) | H11: =INDEX('Pipeline A-B'!$Q$2:$Q$132,MATCH($B11,'Pipeline A-B'!$A$2:$A$132,0)) | I11: =INDEX('Pipeline A-B'!$K$2:$K$132,MATCH($B11,'Pipeline A-B'!$A$2:$A$132,0)) | J11: =INDEX('Pipeline A-B'!$L$2:$L$132,MATCH($B11,'Pipeline A-B'!$A$2:$A$132,0)) | K11: =INDEX('Pipeline A-B'!$T$2:$T$132,MATCH($B11,'Pipeline A-B'!$A$2:$A$132,0)) | L11: =INDEX('Pipeline A-B'!$R$2:$R$132,MATCH($B11,'Pipeline A-B'!$A$2:$A$132,0))
A12: 11 | B12: S011 | C12: =INDEX('Pipeline A-B'!$B$2:$B$132,MATCH($B12,'Pipeline A-B'!$A$2:$A$132,0)) | D12: =INDEX('Pipeline A-B'!$D$2:$D$132,MATCH($B12,'Pipeline A-B'!$A$2:$A$132,0)) | E12: =INDEX('Pipeline A-B'!$E$2:$E$132,MATCH($B12,'Pipeline A-B'!$A$2:$A$132,0)) | F12: =INDEX('Pipeline A-B'!$M$2:$M$132,MATCH($B12,'Pipeline A-B'!$A$2:$A$132,0)) | G12: =INDEX('Pipeline A-B'!$P$2:$P$132,MATCH($B12,'Pipeline A-B'!$A$2:$A$132,0)) | H12: =INDEX('Pipeline A-B'!$Q$2:$Q$132,MATCH($B12,'Pipeline A-B'!$A$2:$A$132,0)) | I12: =INDEX('Pipeline A-B'!$K$2:$K$132,MATCH($B12,'Pipeline A-B'!$A$2:$A$132,0)) | J12: =INDEX('Pipeline A-B'!$L$2:$L$132,MATCH($B12,'Pipeline A-B'!$A$2:$A$132,0)) | K12: =INDEX('Pipeline A-B'!$T$2:$T$132,MATCH($B12,'Pipeline A-B'!$A$2:$A$132,0)) | L12: =INDEX('Pipeline A-B'!$R$2:$R$132,MATCH($B12,'Pipeline A-B'!$A$2:$A$132,0))
A13: 12 | B13: S012 | C13: =INDEX('Pipeline A-B'!$B$2:$B$132,MATCH($B13,'Pipeline A-B'!$A$2:$A$132,0)) | D13: =INDEX('Pipeline A-B'!$D$2:$D$132,MATCH($B13,'Pipeline A-B'!$A$2:$A$132,0)) | E13: =INDEX('Pipeline A-B'!$E$2:$E$132,MATCH($B13,'Pipeline A-B'!$A$2:$A$132,0)) | F13: =INDEX('Pipeline A-B'!$M$2:$M$132,MATCH($B13,'Pipeline A-B'!$A$2:$A$132,0)) | G13: =INDEX('Pipeline A-B'!$P$2:$P$132,MATCH($B13,'Pipeline A-B'!$A$2:$A$132,0)) | H13: =INDEX('Pipeline A-B'!$Q$2:$Q$132,MATCH($B13,'Pipeline A-B'!$A$2:$A$132,0)) | I13: =INDEX('Pipeline A-B'!$K$2:$K$132,MATCH($B13,'Pipeline A-B'!$A$2:$A$132,0)) | J13: =INDEX('Pipeline A-B'!$L$2:$L$132,MATCH($B13,'Pipeline A-B'!$A$2:$A$132,0)) | K13: =INDEX('Pipeline A-B'!$T$2:$T$132,MATCH($B13,'Pipeline A-B'!$A$2:$A$132,0)) | L13: =INDEX('Pipeline A-B'!$R$2:$R$132,MATCH($B13,'Pipeline A-B'!$A$2:$A$132,0))
... A41: 40 | B41: S040 | C41: =INDEX('Pipeline A-B'!$B$2:$B$132,MATCH($B41,'Pipeline A-B'!$A$2:$A$132,0)) | D41: =INDEX('Pipeline A-B'!$D$2:$D$132,MATCH($B41,'Pipeline A-B'!$A$2:$A$132,0)) | E41: =INDEX('Pipeline A-B'!$E$2:$E$132,MATCH($B41,'Pipeline A-B'!$A$2:$A$132,0)) | F41: =INDEX('Pipeline A-B'!$M$2:$M$132,MATCH($B41,'Pipeline A-B'!$A$2:$A$132,0)) | G41: =INDEX('Pipeline A-B'!$P$2:$P$132,MATCH($B41,'Pipeline A-B'!$A$2:$A$132,0)) | H41: =INDEX('Pipeline A-B'!$Q$2:$Q$132,MATCH($B41,'Pipeline A-B'!$A$2:$A$132,0)) | I41: =INDEX('Pipeline A-B'!$K$2:$K$132,MATCH($B41,'Pipeline A-B'!$A$2:$A$132,0)) | J41: =INDEX('Pipeline A-B'!$L$2:$L$132,MATCH($B41,'Pipeline A-B'!$A$2:$A$132,0)) | K41: =INDEX('Pipeline A-B'!$T$2:$T$132,MATCH($B41,'Pipeline A-B'!$A$2:$A$132,0)) | L41: =INDEX('Pipeline A-B'!$R$2:$R$132,MATCH($B41,'Pipeline A-B'!$A$2:$A$132,0))
C43: Order is a snapshot of priority on 24 Oct 2026. Details update live from 'Pipeline A-B'; to re-rank, sort that sheet by Priority score.

Sheet Partners & media
A1: Organisation | B1: Edition | C1: Why it matters | D1: Evidence URL | E1: Next action
A2: CCIFP (Franco-Portuguese Chamber) | B2: FR | C2: Created the Paris Portuguese property fair; members are our FR sponsors | D2: https://www.idealista.pt/news/node/59586 | E2: Ask for member directory and a joint webinar
A3: Salon de l'immobilier et de l'investissement portugais (Paris) | B3: FR | C3: ~150 exhibitors and ~10,000 visitors per edition: the exhibitor list is a ready-made sponsor list | D3: https://lusojornal.com/salao-do-imobiliario-e-do-investimento-portugues-muda-se-para-a-porte-de-champeret/ | E3: Get the latest exhibitor list; visit next edition
A4: CCISSP (Swiss–Portuguese Chamber, Geneva) | B4: CH | C4: Organised a Portuguese property fair in Geneva (2020) | D4: https://www.idealista.pt/news/node/43936 | E4: Ask for member directory and event partnership
A5: Chambre de Commerce Luxembourg | B5: LU | C5: Runs the Luxembourg–Portugal Business Forum | D5: https://cc.lu/agenda/detail/luxembourg-portugal-business-forum | E5: Attend the next forum
A6: Decisão magazine / Paperjam 10x6 | B6: LU | C6: Portuguese business community in Luxembourg; event on 10 Nov 2026, Kinepolis Kirchberg | D6: https://en.paperjam.lu/club/event/paperjam-10x6-decisao-the-portuguese-business-community-in-action | E6: Partner attends and collects contacts
A7: LusoJornal | B7: FR | C7: Weekly Franco-Portuguese paper; its advertisers are proven sponsors | D7: https://lusojornal.com/salao-do-imobiliario-e-do-investimento-portugues-muda-se-para-a-porte-de-champeret/ | E7: Content swap; monitor advertisers monthly
A8: Lusopress | B8: FR, PT | C8: Diaspora magazine; ad concession Boomerang – Multimédia e Comunicação | D8: https://lusopress.tv/wp-content/uploads/2025/12/Revista-142.pdf | E8: Ask the ad concessionaire who buys diaspora ads
A9: Academia do Bacalhau de Paris | B9: FR | C9: Network of Portuguese business owners in Paris; sponsors include BCP, CGD, Fidelidade | D9: https://lusopress.tv/wp-content/uploads/2023/07/lusopress_125.pdf | E9: Introduction to members
A10: Rádio Alfa | B10: FR | C10: Portuguese radio in Paris; media supporter of community events | D10: https://lusopress.tv/wp-content/uploads/2023/07/lusopress_125.pdf | E10: Content swap / joint segment
A11: Rádio Latina | B11: LU | C11: Portuguese radio in Luxembourg | D11: https://en.paperjam.lu/guide/organisation/01276932145/radio-latina | E11: Content swap / joint segment
A12: Contacto | B12: LU | C12: Portuguese newspaper in Luxembourg | D12: https://en.wikipedia.org/wiki/Contacto_(Luxembourg) | E12: Monitor advertisers; content swap
A13: Eurodicas | B13: BR | C13: Large Brazilian site on living in Portugal; its partners and affiliates are proven BR sponsors (competitor and channel) | D13: https://www.eurodicas.com.br/comprar-casa-em-portugal/ | E13: Monitor partners monthly
A15: Not sponsors: they give access to sponsors, audience or intelligence on who buys diaspora ads.

Sheet Exit buyers
A1: Possible buyer | B1: Type | C1: Why they would buy | D1: Evidence URL
A2: idealista | B2: Portal | C2: Announced purchase of Kyero (international buyers) in 2024; deal abandoned in 2025 after CNMC conditions | D2: https://www.onlinemarketplaces.com/articles/idealistas-kyero-acquisition-cancelled-as-competition-authority-steps-in/
A3: Kyero | B3: Portal for international buyers | C3: Plans to reinvest in growth after the failed idealista deal | D3: https://www.onlinemarketplaces.com/articles/idealistas-kyero-acquisition-cancelled-as-competition-authority-steps-in/
A4: Green-Acres | B4: Second-home portal | C4: 56 countries, 20 languages; agency subscriptions | D4: https://www.luxinmo.com/portals/green-acres
A5: A Place in the Sun | B5: Overseas property media | C5: Same media + fairs model, UK audience | D5: https://www.aplaceinthesun.com/advertise/magazine
A6: Portugal Homes | B6: Agency for international buyers | C6: Would buy a ready audience of foreign buyers | D6: https://www.portugalhomes.com/pt/move-to-portugal/services/property-management
A7: Imovirtual | B7: Portal | C7: Portuguese portal; diaspora audience is a gap
A8: Casa Sapo | B8: Portal | C8: Portuguese portal; diaspora audience is a gap
A9: RE/MAX Portugal / ERA / Zome | B9: Agency networks | C9: Lead source for emigrant sellers and buyers
A10: LusoJornal / Lusopress | B10: Diaspora media | C10: Consolidation of diaspora media | D10: https://lusojornal.com/salao-do-imobiliario-e-do-investimento-portugues-muda-se-para-a-porte-de-champeret/

Sheet Chambers & embassies
A1: Organisation | B1: Type | C1: Country | D1: What they offer | E1: Public contact route | F1: Evidence URL | G1: Evidence check | H1: Relevance | I1: Next action
A2: AmCham Portugal (Câmara de Comércio Americana em Portugal) | B2: Chamber | C2: USA | D2: Private non-profit bilateral chamber, about 300 member companies; monthly newsletter; more than 40 events a year; 49 sponsors in Platinum, Gold and Silver tiers (own site) | E2: Contact form on the site (Contactos page) | F2: https://amchamportugal.pt | G2: Fetched | H2: High for the US edition: the one organisation that reaches US companies in Portugal | I2: Ask for sponsor and newsletter options; offer a labelled guest post
A3: British-Portuguese Chamber of Commerce (BPCC) | B3: Chamber | C3: United Kingdom | D3: Founded 1911, about 350 members, offices in Lisbon, the North and the Algarve; an advertising service and a mailing list (no prices published) | E3: Contacts page on the site | F3: https://bpcc.pt | G3: Fetched | H3: Low: there is no UK edition. Savills Portugal is a member (an agency, D9) | I3: Park until a UK edition exists
A4: Portuguese Chamber of Commerce in the UK (PCCUK) | B4: Chamber | C4: United Kingdom | D4: Runs the Moving to Portugal show and seminars with AICEP, four a year (London 26 Mar 2026; London 15 Oct 2026; Edinburgh 12 Nov 2026); free for visitors; exhibitors include resorts, banks, tax advisers | E4: Via the show's website or AICEP (public line on the Portugal Global page) | F4: https://portugalglobal.pt/en/news/2026/fevereiro/moving-to-portugal-show-and-seminars-returns-to-central-london | G4: Fetched | H4: Low: UK audience, no UK edition; useful as a model for a US show | I4: Park
A5: Portugal-China Chamber of Commerce and Industry (CCILC) | B5: Chamber | C5: China | D5: Lisbon chamber founded in 1978, about 200 member companies (undated EU SME Centre profile); a Sept 2026 item reports a new corporate member | E5: Via its website (not opened) | F5: https://www.eusmecentre.org.cn/partners/portugal-china-chamber-of-commerce-and-industry-ccilc | G5: Search result | H5: Low: no Chinese edition and no current Chinese residential developer found | I5: Park; re-check if a Chinese-language edition is ever planned
A6: Portuguese-Israeli Chamber of Commerce (CCLI) | B6: Chamber | C6: Israel | D6: Reported by Portugal Resident as a newly formed chamber that held a lunch in Porto for about 50 people; the article is undated and no current website was found | E6: Unknown | F6: https://www.portugalresident.com/chamber/ | G6: Search result | H6: High if it exists: the natural door to Israeli developers in Porto | I6: Daniel or the partner to confirm the chamber exists and who runs it
A7: U.S. Commercial Service, Embassy of the United States in Lisbon | B7: Embassy | C7: USA | D7: Helps US companies export to Portugal; office inside the embassy compound; the site lists a public office line and staff names that differ between pages | E7: Office contact on the trade.gov Portugal page | F7: https://www.trade.gov/portugal-contact-us | G7: Search result | H7: Low: it serves US exporters, not buyers. Ask only whether it can share a note with US firms active in Portuguese real estate | I7: Formal introduction request, no logo or endorsement
A8: Embassy of the United Kingdom in Lisbon, Department for Business and Trade | B8: Embassy | C8: United Kingdom | D8: Directs UK companies that want to export or invest in Portugal to a public enquiries mailbox | E8: Public enquiries route on the gov.uk page | F8: https://www.gov.uk/world/organisations/british-embassy-lisbon/office/department-for-business-and-trade | G8: Fetched | H8: Low: no UK edition | I8: Park
A9: Embassy of Israel in Lisbon | B9: Embassy | C9: Israel | D9: Public site with the embassy's departments and social accounts. No economic or trade section page was found; Israel's missions often have one inside the Foreign Trade Administration, but this is not confirmed for Lisbon | E9: Enquiry route on the embassy site | F9: https://embassies.gov.il/portugal/en | G9: Search result | H9: Medium for the IL edition, once the economic section is identified | I9: Find the economic section (task for Daniel); then a formal introduction request
A10: Embassy of China in Lisbon, Economic and Commercial Counsellor's Office | B10: Embassy | C10: China | D10: Mandate (2015 Ministry of Commerce page): promote bilateral trade and investment, advise firms, organise fairs and seminars; no public contact route found | E10: Via the embassy's official site (not opened) | F10: https://pt.mofcom.gov.cn/AboutUs/art/2015/art_1d0f6ff0306d46a1b7192aa708363bfb.html | G10: Search result | H10: Low | I10: Park
A12: Introductions only: no endorsement requested, no embassy or chamber name or logo on our site or media kit. No personal emails are stored.

Sheet Excluded (agencies)
A1: Company | B1: Sector | C1: Tier | D1: Evidence URL | E1: Why excluded
A2: 7 Adresses | B2: Agency | C2: A | D2: https://www.idealista.pt/news/node/26913 | E2: Real-estate agency: competes with the partner agency (decision D9)
A3: Century 21 Portugal | B3: Agency network | C3: C | E3: Real-estate agency: competes with the partner agency (decision D9)
A4: Conexão Europa Imóveis | B4: Buying advice / property management | C4: A | D4: https://www.eurodicas.com.br/conexao-europa-imoveis/ | E4: Real-estate agency: competes with the partner agency (decision D9)
A5: Dils | B5: Agency | C5: B | D5: https://dnbrasil.dn.pt/o-brasileiro-o-nosso-principal-cliente-afirma-gestora-de-imobiliria-de-alto-padro-em-portugal | E5: Real-estate agency: competes with the partner agency (decision D9)
A6: ERA Avenidas Novas | B6: Agency | C6: A | D6: https://www.idealista.pt/news/node/26913 | E6: Real-estate agency: competes with the partner agency (decision D9)
A7: Engel & Völkers Portugal | B7: Agency | C7: A | D7: https://www.idealista.pt/news/node/26913 | E7: Real-estate agency: competes with the partner agency (decision D9)
A8: Faccin Investments | B8: Property consultancy | C8: B | D8: https://investnews.com.br/financas/entre-estrangeiros-brasileiros-lideram-busca-por-imoveis-de-luxo-em-pontos-nobres-de-portugal/amp/ | E8: Real-estate agency: competes with the partner agency (decision D9)
A9: Flávia Motta | B9: Broker (Brazilian clients) | C9: B | D9: https://dnbrasil.dn.pt/flávia-motta-a-carioca-que-virou-referência-para-brasileiros-no-mercado-imobiliário-português | E9: Real-estate agency: competes with the partner agency (decision D9)
A10: Fábio Neves Imobiliária | B10: Agency | C10: A | D10: https://www.theportugalnews.com/pt/noticias/2026-05-08/fabio-neves-imobiliaria-ajuda-compradores-internacionais-a-mudarem-se-e-a-investirem-em-portugal/1017957 | E10: Real-estate agency: competes with the partner agency (decision D9)
A11: Homelovers | B11: Agency | C11: A | D11: https://www.idealista.pt/news/node/26913 | E11: Real-estate agency: competes with the partner agency (decision D9)
A12: Infante & Riu | B12: Agency | C12: A | D12: https://www.idealista.pt/news/node/26913 | E12: Real-estate agency: competes with the partner agency (decision D9)
A13: Judice & Araújo | Christie's | B13: Agency (Rio de Janeiro) | C13: A | D13: https://monitormercantil.com.br/mercado-imobili-rio-de-portugal-op-o-para-a-investidores-brasileiros/ | E13: Real-estate agency: competes with the partner agency (decision D9)
A14: KW Portugal | B14: Agency network | C14: C | E14: Real-estate agency: competes with the partner agency (decision D9)
A15: Libertas / Maison au Portugal | B15: Agency / developer | C15: A | D15: https://libertas.pt/fr/decouvrez-limmobilier-portugais-au-salon-de-linvestissement-de-paris/ | E15: Real-estate agency: competes with the partner agency (decision D9)
A16: Maia International Properties | B16: Agency (Brazilian buyers) | C16: A | D16: https://diariodocomercio.com.br/negocios/imobiliaria-boutique-portugal-luiz-felipe-maia/ | E16: Real-estate agency: competes with the partner agency (decision D9)
A17: Oliveira Imóveis | B17: Buying consultancy (Brazilian buyers) | C17: A | D17: https://www.eurodicas.com.br/comprar-casa-em-portugal/ | E17: Real-estate agency: competes with the partner agency (decision D9)
A18: Porta da Frente | Christie's | B18: Agency (Lisbon) | C18: A | D18: https://monitormercantil.com.br/mercado-imobili-rio-de-portugal-op-o-para-a-investidores-brasileiros/ | E18: Real-estate agency: competes with the partner agency (decision D9)
A19: Portugal Homes | B19: Agency / relocation | C19: B | D19: https://www.portugalhomes.com/pt/move-to-portugal/services/property-management | E19: Real-estate agency: competes with the partner agency (decision D9)
A20: Portugal Sotheby's International Realty | B20: Agency | C20: C | E20: Real-estate agency: competes with the partner agency (decision D9)
A21: Quintela & Penalva | B21: Agency | C21: A | D21: https://www.idealista.pt/news/node/26913 | E21: Real-estate agency: competes with the partner agency (decision D9)
A22: RE/MAX Alcateia | B22: Agency | C22: A | D22: https://investnews.com.br/financas/entre-estrangeiros-brasileiros-lideram-busca-por-imoveis-de-luxo-em-pontos-nobres-de-portugal/amp/ | E22: Real-estate agency: competes with the partner agency (decision D9)
A23: RE/MAX Portugal (central) | B23: Agency network | C23: C | E23: Real-estate agency: competes with the partner agency (decision D9)
A24: Stay Properties | B24: Agency / rentals | C24: A | D24: https://www.idealista.pt/news/node/26913 | E24: Real-estate agency: competes with the partner agency (decision D9)
A25: Zome | B25: Agency network | C25: C | E25: Real-estate agency: competes with the partner agency (decision D9)
A26: immoabroad | B26: Portal / agency | C26: B | D26: https://www.immoabroad.com/portugal/buying-a-house-in-portugal-full-guide-for-foreigners-2025 | E26: Real-estate agency: competes with the partner agency (decision D9)

Sheet Settings
A1: Settings: edit the yellow cells; every value in the workbook updates
A3: Offer type | B3: Price year 1 (€) | C3: Basis
A4: Gold | B4: 4800 | C4: 8,000 €/yr list price, 40% founding discount
A5: Silver | B5: 1800 | C5: 3,000 €/yr list, 40% founding discount
A6: Bronze | B6: 540 | C6: 900 €/yr list, 40% founding discount
A7: Campaign | B7: 1500 | C7: One developer campaign
A8: Featured listings | B8: 1200 | C8: ~5 listings x 12 months at reduced pilot rate
A9: Affiliate | B9: 600 | C9: Estimated affiliate income per year
A10: Affiliate + sponsor | B10: 1800 | C10: Affiliate income plus a Silver slot
A11: Verified Partner | B11: 1080 | C11: v3 proposal: 1,800 € per edition per year, 40% founding discount
A12: Featured Partner | B12: 2880 | C12: v3 proposal: 4,800 € per edition per year, 40% founding discount
A13: Bank Partner | B13: 5400 | C13: v3 proposal: 9,000 to 15,000 € per year, founding price on the low end
A14: Developer campaign | B14: 2500 | C14: v3 proposal: from 2,500 € per campaign
A15: Private Partner | B15: 15000 | C15: v3 proposal (D33): 25,000 to 50,000 € per year, founding price on the low end
A17: Close probability | B17: Value | C17: Meaning
A18: Tier A, evidence 2022 or later | B18: 0.25 | C18: Proven recent spend on our audience
A19: Tier A, older evidence | B19: 0.15 | C19: Proven spend before 2022; re-verify
A20: Tier B | B20: 0.12 | C20: Serves our audience, no proof of spend
A21: Tier C | B21: 0.04 | C21: Large or generic, long cycle
A22: Bonus for small company | B22: 0.05 | C22: Owner decides fast
A24: Size | B24: Speed factor | C24: Meaning
A25: S | B25: 1.5 | C25: Small: decides in days
A26: M | B26: 1 | C26: Mid-size: weeks
A27: L | B27: 0.6 | C27: Large: months
A29: Prices follow the current plan. If Daniel picks lower pre-launch pricing (decision D3), change column B above.
