Workbook

Sheet Resumo
A1: Resumo da lista
A3: Setor | B3: Empresas | C3: Prioridade 1 | D3: Fechados
A4: Bancos e crédito | B4: =COUNTIF('Lista 100'!$C$2:$C$101,A4) -> 22 | C4: =COUNTIFS('Lista 100'!$C$2:$C$101,A4,'Lista 100'!$E$2:$E$101,1) -> 5 | D4: =COUNTIFS('Lista 100'!$C$2:$C$101,A4,'Lista 100'!$L$2:$L$101,"Fechado") -> 0
A5: Câmbio e transferências | B5: =COUNTIF('Lista 100'!$C$2:$C$101,A5) -> 11 | C5: =COUNTIFS('Lista 100'!$C$2:$C$101,A5,'Lista 100'!$E$2:$E$101,1) -> 3 | D5: =COUNTIFS('Lista 100'!$C$2:$C$101,A5,'Lista 100'!$L$2:$L$101,"Fechado") -> 0
A6: Advogados e imigração | B6: =COUNTIF('Lista 100'!$C$2:$C$101,A6) -> 19 | C6: =COUNTIFS('Lista 100'!$C$2:$C$101,A6,'Lista 100'!$E$2:$E$101,1) -> 6 | D6: =COUNTIFS('Lista 100'!$C$2:$C$101,A6,'Lista 100'!$L$2:$L$101,"Fechado") -> 0
A7: Fiscalidade e pensões | B7: =COUNTIF('Lista 100'!$C$2:$C$101,A7) -> 5 | C7: =COUNTIFS('Lista 100'!$C$2:$C$101,A7,'Lista 100'!$E$2:$E$101,1) -> 1 | D7: =COUNTIFS('Lista 100'!$C$2:$C$101,A7,'Lista 100'!$L$2:$L$101,"Fechado") -> 0
A8: Promotores imobiliários | B8: =COUNTIF('Lista 100'!$C$2:$C$101,A8) -> 10 | C8: =COUNTIFS('Lista 100'!$C$2:$C$101,A8,'Lista 100'!$E$2:$E$101,1) -> 4 | D8: =COUNTIFS('Lista 100'!$C$2:$C$101,A8,'Lista 100'!$L$2:$L$101,"Fechado") -> 0
A9: Agências imobiliárias | B9: =COUNTIF('Lista 100'!$C$2:$C$101,A9) -> 9 | C9: =COUNTIFS('Lista 100'!$C$2:$C$101,A9,'Lista 100'!$E$2:$E$101,1) -> 1 | D9: =COUNTIFS('Lista 100'!$C$2:$C$101,A9,'Lista 100'!$L$2:$L$101,"Fechado") -> 0
A10: Seguros | B10: =COUNTIF('Lista 100'!$C$2:$C$101,A10) -> 6 | C10: =COUNTIFS('Lista 100'!$C$2:$C$101,A10,'Lista 100'!$E$2:$E$101,1) -> 0 | D10: =COUNTIFS('Lista 100'!$C$2:$C$101,A10,'Lista 100'!$L$2:$L$101,"Fechado") -> 0
A11: Gestão de arrendamento | B11: =COUNTIF('Lista 100'!$C$2:$C$101,A11) -> 4 | C11: =COUNTIFS('Lista 100'!$C$2:$C$101,A11,'Lista 100'!$E$2:$E$101,1) -> 0 | D11: =COUNTIFS('Lista 100'!$C$2:$C$101,A11,'Lista 100'!$L$2:$L$101,"Fechado") -> 0
A12: Obras, casa e energia | B12: =COUNTIF('Lista 100'!$C$2:$C$101,A12) -> 8 | C12: =COUNTIFS('Lista 100'!$C$2:$C$101,A12,'Lista 100'!$E$2:$E$101,1) -> 0 | D12: =COUNTIFS('Lista 100'!$C$2:$C$101,A12,'Lista 100'!$L$2:$L$101,"Fechado") -> 0
A13: Mudanças e viagens | B13: =COUNTIF('Lista 100'!$C$2:$C$101,A13) -> 6 | C13: =COUNTIFS('Lista 100'!$C$2:$C$101,A13,'Lista 100'!$E$2:$E$101,1) -> 0 | D13: =COUNTIFS('Lista 100'!$C$2:$C$101,A13,'Lista 100'!$L$2:$L$101,"Fechado") -> 0
A14: Total | B14: =SUM(B4:B13) -> 100 | C14: =SUM(C4:C13) -> 20 | D14: =SUM(D4:D13) -> 0
A16: Edição | B16: Empresas que a incluem
A17: LU | B17: =SUMPRODUCT(--((ISNUMBER(SEARCH("LU",'Lista 100'!$D$2:$D$101))+ISNUMBER(SEARCH("Todas",'Lista 100'!$D$2:$D$101)))>0)) -> 72
A18: FR | B18: =SUMPRODUCT(--((ISNUMBER(SEARCH("FR",'Lista 100'!$D$2:$D$101))+ISNUMBER(SEARCH("Todas",'Lista 100'!$D$2:$D$101)))>0)) -> 66
A19: CH | B19: =SUMPRODUCT(--((ISNUMBER(SEARCH("CH",'Lista 100'!$D$2:$D$101))+ISNUMBER(SEARCH("Todas",'Lista 100'!$D$2:$D$101)))>0)) -> 66
A20: BR | B20: =SUMPRODUCT(--((ISNUMBER(SEARCH("BR",'Lista 100'!$D$2:$D$101))+ISNUMBER(SEARCH("Todas",'Lista 100'!$D$2:$D$101)))>0)) -> 69
A22: 'Todas' conta para as quatro edições; empresas com várias edições contam em cada uma.

Sheet Lista 100
A1: # | B1: Empresa | C1: Setor | D1: Edições | E1: Prioridade | F1: Pacote sugerido | G1: Porque nos paga | H1: Quem procurar | I1: Melhor canal | J1: Site | K1: Verificação | L1: Estado | M1: Quem contacta | N1: Notas
A2: 1 | B2: Caiado Guerreiro | C2: Advogados e imigração | D2: BR, Todas | E2: 1 | F2: Gold | G2: Clientes internacionais e brasileiros; imobiliário e residência | H2: Sócio / Business development | I2: LinkedIn + email | J2: caiadoguerreiro.com | K2: Conhecida — confirmar contacto | L2: Por contactar
A3: 2 | B3: Antas da Cunha Ecija | C3: Advogados e imigração | D3: BR, Todas | E3: 1 | F3: Gold | G3: Forte em clientes brasileiros | H3: Sócio / Business development | I3: LinkedIn + email | J3: antasdacunha.pt | K3: Conhecida — confirmar contacto | L3: Por contactar
A4: 3 | B4: RFF Lawyers | C4: Advogados e imigração | D4: Todas | E4: 1 | F4: Gold | G4: Fiscalidade de não residentes e de quem regressa | H4: Sócio / Marketing | I4: LinkedIn + email | J4: rfflawyers.com | K4: Conhecida — confirmar contacto | L4: Por contactar
A5: 4 | B5: LVP Advogados | C5: Advogados e imigração | D5: Todas | E5: 1 | F5: Gold | G5: Diz servir clientes de mais de 150 países em investimentos em Portugal | H5: Sócio | I5: Email | J5: lvpadvogados.com | K5: Confirmado na pesquisa | L5: Por contactar
A6: 5 | B6: Martins Castro | C6: Advogados e imigração | D6: Todas | E6: 1 | F6: Gold | G6: Imobiliário e imigração para estrangeiros | H6: Sócio | I6: Email | J6: martinscastro.pt | K6: Conhecida — confirmar contacto | L6: Por contactar
A7: 6 | B7: Silva Avocat & Partners | C7: Advogados e imigração | D7: FR | E7: 1 | F7: Silver | G7: Advogada inscrita em Paris e Lisboa; trabalha em francês e português | H7: Fundadora | I7: LinkedIn | J7: a confirmar | K7: Confirmado na pesquisa | L7: Por contactar
A8: 7 | B8: Fábio Neves Imobiliária | C8: Agências imobiliárias | D8: LU, FR | E8: 1 | F8: Gold | G8: Escritórios no Luxemburgo, em França e no Alto Minho; foco em compradores de fora | H8: Fundador | I8: Email + LinkedIn | J8: fabioneves.pt | K8: Confirmado na pesquisa | L8: Por contactar
A9: 8 | B9: Caixa Geral de Depósitos | C9: Bancos e crédito | D9: LU, FR | E9: 1 | F9: Gold | G9: Sucursal em França e escritório de representação no Luxemburgo; o emigrante é cliente histórico | H9: Marketing / Rede internacional | I9: LinkedIn + email institucional | J9: cgd.pt | K9: Confirmado na pesquisa | L9: Por contactar
A10: 9 | B10: Millennium bcp | C10: Bancos e crédito | D10: FR, LU, CH | E10: 1 | F10: Gold | G10: Tem área dedicada a residentes em França; crédito habitação a não residentes | H10: Marketing / Residentes no estrangeiro | I10: LinkedIn | J10: millenniumbcp.pt | K10: Confirmado na pesquisa | L10: Por contactar
A11: 10 | B11: Banque BCP (França) | C11: Bancos e crédito | D11: FR | E11: 1 | F11: Gold | G11: Banco francês nascido na comunidade portuguesa; financia compras em Portugal | H11: Marketing / Diretor de agência | I11: Email + visita a agência | J11: banquebcp.fr | K11: Confirmado na pesquisa | L11: Por contactar
A12: 11 | B12: Novo Banco | C12: Bancos e crédito | D12: Todas | E12: 1 | F12: Gold | G12: Oferta para emigrantes e não residentes | H12: Marketing / Segmento emigrantes | I12: LinkedIn | J12: novobanco.pt | K12: Conhecida — confirmar contacto | L12: Por contactar
A13: 12 | B13: Doutor Finanças | C13: Bancos e crédito | D13: Todas | E13: 1 | F13: Gold | G13: Intermediário de crédito com conteúdo sobre crédito a emigrantes | H13: Marketing / Parcerias | I13: Email parcerias | J13: doutorfinancas.pt | K13: Confirmado na pesquisa | L13: Por contactar
... A101: 100 | B101: Lalux | C101: Seguros | D101: LU | E101: 3 | F101: Bronze | G101: Seguradora luxemburguesa | H101: Marketing | I101: LinkedIn | J101: lalux.lu | K101: Conhecida — confirmar contacto | L101: Por contactar
B103: Preencher: colunas Estado (lista), Quem contacta e Notas. Prioridade 1 = contactar nas 2 primeiras semanas. 'Conhecida — confirmar contacto' = empresa real, falta confirmar a pessoa certa no LinkedIn ou no site.

Sheet Setores e abordagem
A1: Setor | B1: Porque nos pagam | C1: Quem procurar | D1: Melhor maneira de contactar | E1: Pacote | F1: Nota
A2: Bancos e crédito | B2: O crédito é o maior produto de cada compra. Os bancos portugueses com presença em França, Luxemburgo e Suíça já procuram este cliente. | C2: Responsável de marketing ou do segmento 'residentes no estrangeiro'; em França, também os diretores de agência. | D2: LinkedIn primeiro, depois email institucional. Ciclo longo (2 a 3 meses): propor um piloto de 3 meses numa só edição. | E2: Gold 8.000–12.000 €/ano | F2: Têm orçamento, mas decidem devagar. Começar pelos intermediários de crédito, que decidem em dias.
A3: Câmbio e transferências | B3: Quem compra com francos ou reais transfere centenas de milhares de euros. Cada cliente vale muito. | C3: Partnerships / affiliates. | D3: Muitos têm programas de afiliados ou de introdutores: inscrever primeiro (receita por cliente), depois propor patrocínio. | E3: Gold, ou comissão por cliente | F3: Edições CH e BR são as mais valiosas para eles.
A4: Advogados e imigração | B4: Cada compra precisa de escritura, procuração, partilhas ou visto. Um cliente vale milhares em honorários. | C4: Sócio de imobiliário ou responsável de business development. Nos pequenos, o fundador. | D4: Email curto + LinkedIn ao sócio. Oferecer a coluna 'Pergunte ao advogado' e exclusividade de categoria. | E4: Gold 8.000–12.000 €/ano ou Silver | F4: Decidem rápido. Confirmar regras de publicidade da Ordem dos Advogados para o formato (EOA, art. 94.º).
A5: Fiscalidade e pensões | B5: Impostos de não residente, rendas, regresso e levantamento do 2.º pilar suíço: dúvidas recorrentes todos os anos. | C5: Fundador ou marketing. | D5: Email com um artigo-amostra sobre o tema deles. | E5: Silver; Gold para pensões na Suíça | F5: O 2.º pilar suíço é o tema mais forte da edição CH.
A6: Promotores imobiliários | B6: Precisam de vender frações a estrangeiros e já pagam campanhas. | C6: Diretor comercial ou de marketing. | D6: LinkedIn + email com proposta de campanha para um empreendimento concreto. | E6: Campanha a partir de 1.500 € | F6: Pagam por campanha, não por ano. Bons para receita rápida.
A7: Agências imobiliárias | B7: Destaque dos imóveis junto de compradores que vivem fora. | C7: Diretor de agência ou fundador. | D7: Email + chamada. Nas redes (RE/MAX, ERA), falar com cada agência, não com a central. | E7: Destaques 49–99 €/imóvel/mês | F7: Atenção ao conflito com a agência parceira: definir quem recebe os pedidos.
A8: Seguros | B8: Seguro de casa e de vida em cada compra com crédito. | C8: Marketing. | D8: LinkedIn. | E8: Silver | F8: Prioridade baixa: decidem devagar e os mediadores já os vendem.
A9: Gestão de arrendamento | B9: Quem compra e ainda vive fora precisa de alguém que gira a casa. | C9: Partnerships ou fundador. | D9: Email. | E9: Silver | F9: Muitas têm programas de referência.
A10: Obras, casa e energia | B10: Quem herda ou compra casa antiga precisa de a recuperar à distância. | C10: Marketing. | D10: Email. | E10: Silver / Bronze | F10: Fixando e Zaask são os mais alinhados.
A11: Mudanças e viagens | B11: Quem regressa leva a casa inteira; a TAP vive da diáspora. | C11: Marketing ou comercial. | D11: Email; TAP por LinkedIn. | E11: Bronze; Gold para a TAP | F11: A TAP é difícil, mas um contrato dá credibilidade a todos os outros.

Sheet Sequência e emails
A1: Sequência
A2: Dia 0 | B2: Email curto à pessoa certa (ou ao email geral, se não houver).
A3: Dia 2 | B3: Pedido de ligação no LinkedIn, sem pitch, só uma frase.
A4: Dia 5 | B4: Follow-up de duas linhas no mesmo email.
A5: Dia 9 | B5: Último follow-up com uma data concreta para chamada. Se não responder, marcar 'Recusou' e voltar daqui a 3 meses.
A6: Ritmo | B6: 40 contactos novos por semana nas primeiras 6 semanas. Prioridade 1 primeiro.
A7: RGPD | B7: Usar emails profissionais ou gerais da empresa. Cada email termina com uma linha para a pessoa dizer que não quer ser contactada. Interesse legítimo (RGPD, art. 6.º, n.º 1, al. f)).
A9: Email PT
A10: Assunto | B10: Leitores em [país] a comprar casa em Portugal
A11: Corpo | B11: Olá [Nome], Lançamos em janeiro o Imóveis Portugal, um guia com edições no Luxemburgo, em França, na Suíça e no Brasil para quem vive fora e quer comprar casa em Portugal. Falamos de custos reais, crédito, impostos e regresso, com uma newsletter semanal por país. Estamos a escolher um parceiro por categoria e pensámos na [Empresa] para [categoria]. Os primeiros dez parceiros têm 40% de desconto no primeiro ano e o preço fica fixo no segundo. Tem 15 minutos na próxima semana para lhe mostrar o formato? Obrigado, [Nome] Parcerias · Imóveis Portugal Se preferir não receber mais emails nossos, basta responder a dizer.
A12: Follow-up PT | B12: Olá [Nome], volto só a este email. Ainda temos lugar para [categoria] na edição de [país]. Faz sentido falarmos na [dia]?
A14: Email FR
A15: Objet | B15: Lecteurs en France qui achètent au Portugal
A16: Corps | B16: Bonjour [Prénom], Nous lançons en janvier Imóveis Portugal, un guide avec des éditions au Luxembourg, en France, en Suisse et au Brésil pour ceux qui vivent à l'étranger et veulent acheter au Portugal : coûts réels, crédit, fiscalité et retour, avec une newsletter hebdomadaire par pays. Nous choisissons un partenaire par catégorie et avons pensé à [Entreprise] pour [catégorie]. Les dix premiers partenaires ont 40 % de remise la première année et un prix bloqué la deuxième. Auriez-vous 15 minutes la semaine prochaine pour que je vous montre le format ? Merci, [Prénom] Partenariats · Imóveis Portugal Si vous préférez ne plus recevoir nos messages, il suffit de répondre.

Sheet Parceiros de acesso
A1: Organização | B1: Edição | C1: Para que serve | D1: Site | E1: Verificação
A2: Chambre de Commerce Luxembourg | B2: LU | C2: Organiza o Luxembourg–Portugal Business Forum; acesso a empresas | D2: cc.lu | E2: Confirmado na pesquisa
A3: CCIFP — Câmara de Comércio Franco-Portuguesa | B3: FR | C3: Rede de empresas franco-portuguesas | D3: ccifp.fr | E3: Conhecida — confirmar contacto
A4: Cap Magellan | B4: FR | C4: Associação de jovens lusodescendentes em França; divulgação | D4: capmagellan.com | E4: Confirmado na pesquisa
A5: LusoJornal | B5: FR | C5: Jornal da comunidade em França; troca de conteúdo | D5: lusojornal.com | E5: Confirmado na pesquisa
A6: Contacto | B6: LU | C6: Jornal da comunidade no Luxemburgo; troca de conteúdo | D6: contacto.lu | E6: Conhecida — confirmar contacto
A7: Rádio Latina | B7: LU | C7: Rádio em português no Luxemburgo; divulgação | D7: radiolatina.lu | E7: Conhecida — confirmar contacto
A8: Eurodicas | B8: BR | C8: Site brasileiro sobre vida na Europa; troca de conteúdo | D8: eurodicas.com.br | E8: Confirmado na pesquisa
A10: Não são sponsors: dão acesso a empresas, divulgação ou troca de conteúdo.
